[
  {
    "repo_name": "fnw/DL"
  },
  {
    "repo_name": "mb0/lab"
  },
  {
    "repo_name": "stefk/md"
  },
  {
    "repo_name": "UAEH/weka"
  },
  {
    "repo_name": "hxql/HXQL"
  },
  {
    "repo_name": "ksoska/sp"
  },
  {
    "repo_name": "socam/xiv"
  },
  {
    "repo_name": "xinom/muo"
  },
  {
    "repo_name": "LX3JL/xlxd"
  },
  {
    "repo_name": "cmap/cmapR"
  },
  {
    "repo_name": "hine/darma"
  },
  {
    "repo_name": "hpfem/himg"
  },
  {
    "repo_name": "jubalh/MAT"
  },
  {
    "repo_name": "kuzoo/CAGD"
  },
  {
    "repo_name": "luxas/etcd"
  },
  {
    "repo_name": "memowe/lol"
  },
  {
    "repo_name": "padi/saral"
  },
  {
    "repo_name": "pemre/demo"
  },
  {
    "repo_name": "pi0/AP2014"
  },
  {
    "repo_name": "rxrc/zshrc"
  },
  {
    "repo_name": "skeate/boa"
  },
  {
    "repo_name": "souce/blog"
  },
  {
    "repo_name": "tglima/CRS"
  },
  {
    "repo_name": "xiayan/MTL"
  },
  {
    "repo_name": "1forh/climb"
  },
  {
    "repo_name": "AKBQuiz/Web"
  },
  {
    "repo_name": "Altra/SHINE"
  },
  {
    "repo_name": "adrg/errors"
  },
  {
    "repo_name": "bower/bower"
  },
  {
    "repo_name": "jahshaka/VR"
  },
  {
    "repo_name": "jech/polipo"
  },
  {
    "repo_name": "lbdremy/Bar"
  },
  {
    "repo_name": "lp177/libft"
  },
  {
    "repo_name": "obedmr/ciao"
  },
  {
    "repo_name": "sld/Planamp"
  },
  {
    "repo_name": "sorpaas/rux"
  },
  {
    "repo_name": "zeth/inputs"
  },
  {
    "repo_name": "0xced/nimbus"
  },
  {
    "repo_name": "EManual/task"
  },
  {
    "repo_name": "EduFocal/api"
  },
  {
    "repo_name": "bbog/JSRatio"
  },
  {
    "repo_name": "commontk/CTK"
  },
  {
    "repo_name": "fuulish/surf"
  },
  {
    "repo_name": "hhru/tornado"
  },
  {
    "repo_name": "jwest/MorCMS"
  },
  {
    "repo_name": "karlfl/Prism"
  },
  {
    "repo_name": "leetebbs/BTN"
  },
  {
    "repo_name": "lesunb/goalp"
  },
  {
    "repo_name": "markun9/PSA1"
  },
  {
    "repo_name": "mat-hek/jump"
  },
  {
    "repo_name": "nailor/tirsk"
  },
  {
    "repo_name": "phagara/cogs"
  },
  {
    "repo_name": "praste/maven"
  },
  {
    "repo_name": "pymad/jpymad"
  },
  {
    "repo_name": "scrodde/no44"
  },
  {
    "repo_name": "secdev/scapy"
  },
  {
    "repo_name": "spanners/lod"
  },
  {
    "repo_name": "ssro/scripts"
  },
  {
    "repo_name": "toxidle/test"
  },
  {
    "repo_name": "unixorn/zgen"
  },
  {
    "repo_name": "yisibl/share"
  },
  {
    "repo_name": "ynfin/Skynet"
  },
  {
    "repo_name": "zhujunyong/z"
  },
  {
    "repo_name": "Almost23/Dasm"
  },
  {
    "repo_name": "BE-FE/Appollo"
  },
  {
    "repo_name": "Botize/Botize"
  },
  {
    "repo_name": "DDoS/MCCasino"
  },
  {
    "repo_name": "Day8/re-frame"
  },
  {
    "repo_name": "SMERM/EMUForm"
  },
  {
    "repo_name": "ahawkins/dyno"
  },
  {
    "repo_name": "alimg/maxball"
  },
  {
    "repo_name": "alq666/dogled"
  },
  {
    "repo_name": "baibbc/wftest"
  },
  {
    "repo_name": "boo1ean/wtftm"
  },
  {
    "repo_name": "brigand/react"
  },
  {
    "repo_name": "camsapps/CRRR"
  },
  {
    "repo_name": "cavvia/stella"
  },
  {
    "repo_name": "ceph/collectd"
  },
  {
    "repo_name": "cie/plusminus"
  },
  {
    "repo_name": "daed/wolfgang"
  },
  {
    "repo_name": "denji/tachyon"
  },
  {
    "repo_name": "dialt0ne/misc"
  },
  {
    "repo_name": "earzur/nagios"
  },
  {
    "repo_name": "efrence/forem"
  },
  {
    "repo_name": "fegimanam/crd"
  },
  {
    "repo_name": "gorcz/Nicobar"
  },
  {
    "repo_name": "isaacs/braces"
  },
  {
    "repo_name": "joeytat/Gorge"
  },
  {
    "repo_name": "jpotter/angel"
  },
  {
    "repo_name": "jrodalo/katas"
  },
  {
    "repo_name": "kgn/JSONMagic"
  },
  {
    "repo_name": "kotkade/zweig"
  },
  {
    "repo_name": "lakchote/blog"
  },
  {
    "repo_name": "llemoi/goblin"
  },
  {
    "repo_name": "loganmhb/logd"
  },
  {
    "repo_name": "lortiz30/chat"
  },
  {
    "repo_name": "machito/Ghost"
  },
  {
    "repo_name": "mikebrow/runc"
  },
  {
    "repo_name": "noddos/noddos"
  },
  {
    "repo_name": "omajid/fpaste"
  },
  {
    "repo_name": "planmac/mosql"
  },
  {
    "repo_name": "portphp/excel"
  },
  {
    "repo_name": "ptthiem/nose2"
  },
  {
    "repo_name": "pythonp/pynet"
  },
  {
    "repo_name": "pyupio/safety"
  },
  {
    "repo_name": "say25/desktop"
  },
  {
    "repo_name": "snopoke/randb"
  },
  {
    "repo_name": "vace/blogDomo"
  },
  {
    "repo_name": "ventomin/test"
  },
  {
    "repo_name": "vivocoin/vivo"
  },
  {
    "repo_name": "whazell/Typer"
  },
  {
    "repo_name": "xdth/repeater"
  },
  {
    "repo_name": "xorsnn/elm-sm"
  },
  {
    "repo_name": "yzarubin/bhpq"
  },
  {
    "repo_name": "284km/Bogosort"
  },
  {
    "repo_name": "2DP/githubtest"
  },
  {
    "repo_name": "David90sev/AII"
  },
  {
    "repo_name": "FTPiano/ppsspp"
  },
  {
    "repo_name": "GNOME/libxmlmm"
  },
  {
    "repo_name": "Getingjin/demo"
  },
  {
    "repo_name": "Humbedooh/yamg"
  },
  {
    "repo_name": "Igelinmist/ivi"
  },
  {
    "repo_name": "Miserlou/jsntp"
  },
  {
    "repo_name": "ModingFox/Test"
  },
  {
    "repo_name": "NJUJYB/disYarn"
  },
  {
    "repo_name": "Roendal/Fuzion"
  },
  {
    "repo_name": "TeamBEAR/Gummi"
  },
  {
    "repo_name": "Vashmeed/nVoid"
  },
  {
    "repo_name": "aikei/cryptoch"
  },
  {
    "repo_name": "anjhinz/heroes"
  },
  {
    "repo_name": "anonpain/cache"
  },
  {
    "repo_name": "brahman81/mole"
  },
  {
    "repo_name": "brunothg/PagEE"
  },
  {
    "repo_name": "casaval/Ventus"
  },
  {
    "repo_name": "code-ape/specy"
  },
  {
    "repo_name": "cosino/openwrt"
  },
  {
    "repo_name": "cupsnow/test27"
  },
  {
    "repo_name": "danioso/webapp"
  },
  {
    "repo_name": "ddci/vkfilebot"
  },
  {
    "repo_name": "demangeot/remy"
  },
  {
    "repo_name": "djrobstep/csvx"
  },
  {
    "repo_name": "dpmorel/stores"
  },
  {
    "repo_name": "drosseau/degob"
  },
  {
    "repo_name": "edsrzf/mmap-go"
  },
  {
    "repo_name": "eiro/lua-Spore"
  },
  {
    "repo_name": "ferdkuh/rlkart"
  },
  {
    "repo_name": "fteem/rubylogs"
  },
  {
    "repo_name": "gmlove/bicycle"
  },
  {
    "repo_name": "gomicro/ledger"
  },
  {
    "repo_name": "guruparan18/go"
  },
  {
    "repo_name": "gwatts/iniconf"
  },
  {
    "repo_name": "htoooth/gomake"
  },
  {
    "repo_name": "krajj7/BotHack"
  },
  {
    "repo_name": "lasseebert/swm"
  },
  {
    "repo_name": "lemboung/sikes"
  },
  {
    "repo_name": "mjard/saltmine"
  },
  {
    "repo_name": "mlyko/jsonrpc2"
  },
  {
    "repo_name": "moliyar/Quatna"
  },
  {
    "repo_name": "mxcube/mxcube3"
  },
  {
    "repo_name": "mzhou/opaldist"
  },
  {
    "repo_name": "notzippy/revel"
  },
  {
    "repo_name": "pjBooms/fx2048"
  },
  {
    "repo_name": "pufscar/OpenMP"
  },
  {
    "repo_name": "rvm/pluginator"
  },
  {
    "repo_name": "samliew/wpbase"
  },
  {
    "repo_name": "sdwood68/YAFFA"
  },
  {
    "repo_name": "segfo/ctfTools"
  },
  {
    "repo_name": "sing-group/BEW"
  },
  {
    "repo_name": "soft-matter/mr"
  },
  {
    "repo_name": "tennc/webshell"
  },
  {
    "repo_name": "ulmusic/cs1520"
  },
  {
    "repo_name": "wenhaofan/blog"
  },
  {
    "repo_name": "wikieswan/enyo"
  },
  {
    "repo_name": "wohanley/tears"
  },
  {
    "repo_name": "xkdcc/webstore"
  },
  {
    "repo_name": "yslwjj/XSChart"
  },
  {
    "repo_name": "1WiseFoxx/PY_OS"
  },
  {
    "repo_name": "Honigbaum/mocha"
  },
  {
    "repo_name": "LPP1415/LPP_T_8"
  },
  {
    "repo_name": "RJ/playdar-core"
  },
  {
    "repo_name": "RepIR/RepIRApps"
  },
  {
    "repo_name": "RoGUE655/bstand"
  },
  {
    "repo_name": "Slashgear/ksort"
  },
  {
    "repo_name": "Taekus/fnhasher"
  },
  {
    "repo_name": "Thinkei/eh-myob"
  },
  {
    "repo_name": "ZerbeRz/ZSearch"
  },
  {
    "repo_name": "addisaden/antra"
  },
  {
    "repo_name": "alfa001/eustace"
  },
  {
    "repo_name": "alswnet/ECG-Box"
  },
  {
    "repo_name": "amyjoscelyn/w3r"
  },
  {
    "repo_name": "andiwand/ezname"
  },
  {
    "repo_name": "baijian/apiwall"
  },
  {
    "repo_name": "bdanziger/euler"
  },
  {
    "repo_name": "brotatos/growth"
  },
  {
    "repo_name": "buntine/picster"
  },
  {
    "repo_name": "bunzen/pySSDeep"
  },
  {
    "repo_name": "chapcz/datagrid"
  },
  {
    "repo_name": "cloudhead/vargs"
  },
  {
    "repo_name": "dbmeads/ApplyJS"
  },
  {
    "repo_name": "ddnode/leadtime"
  },
  {
    "repo_name": "devWayne/CliLog"
  },
  {
    "repo_name": "dongziboy/first"
  },
  {
    "repo_name": "dotancohen/wpdb"
  },
  {
    "repo_name": "eolivelli/jcifs"
  },
  {
    "repo_name": "eriksuman/trade"
  },
  {
    "repo_name": "etnetera/jmeter"
  },
  {
    "repo_name": "fritzy/staydown"
  },
  {
    "repo_name": "gaearon/gitbook"
  },
  {
    "repo_name": "gardr/validator"
  },
  {
    "repo_name": "ghassanpl/dsfix"
  },
  {
    "repo_name": "ghspark/android"
  },
  {
    "repo_name": "honnorat/f90nml"
  },
  {
    "repo_name": "infoburp/skinny"
  },
  {
    "repo_name": "jcaspian/utopic"
  },
  {
    "repo_name": "jf-parent/brome"
  },
  {
    "repo_name": "jpoirier/hamsdr"
  },
  {
    "repo_name": "jrstv/VideoCore"
  },
  {
    "repo_name": "k0shk0sh/NewKam"
  },
  {
    "repo_name": "krmit/helloRust"
  },
  {
    "repo_name": "kurazu/promises"
  },
  {
    "repo_name": "lgaind/Project3"
  },
  {
    "repo_name": "madtrick/wsecli"
  },
  {
    "repo_name": "mamort/serendip"
  },
  {
    "repo_name": "mapbox/corslite"
  },
  {
    "repo_name": "marklee77/pydoe"
  },
  {
    "repo_name": "meijieH/Cluster"
  },
  {
    "repo_name": "minosys-jp/FPGA"
  },
  {
    "repo_name": "ngteric/Redmach"
  },
  {
    "repo_name": "pdilung/rbovirt"
  },
  {
    "repo_name": "pffy/php-idxgen"
  },
  {
    "repo_name": "qq635938204/PDF"
  },
  {
    "repo_name": "rkusa/touch-dnd"
  },
  {
    "repo_name": "rmunglez/pebble"
  },
  {
    "repo_name": "simpeg/simpegpf"
  },
  {
    "repo_name": "spongezhang/vlb"
  },
  {
    "repo_name": "uxcn/sh-helpers"
  },
  {
    "repo_name": "verynrivas/calc"
  },
  {
    "repo_name": "vexus2/runnerup"
  },
  {
    "repo_name": "watilde/npmbrew"
  },
  {
    "repo_name": "woyoutlz/papapa"
  },
  {
    "repo_name": "yetwish/Reading"
  },
  {
    "repo_name": "Bobertos/Projekt"
  },
  {
    "repo_name": "DivanteLtd/harem"
  },
  {
    "repo_name": "Eric-Guo/Seti_UX"
  },
  {
    "repo_name": "F483/cc-p2ptrade"
  },
  {
    "repo_name": "Hackerfleet/hfos"
  },
  {
    "repo_name": "Maftouhou/Drupal"
  },
  {
    "repo_name": "OGrueAT/WriteLOG"
  },
  {
    "repo_name": "PIC-27/modularJS"
  },
  {
    "repo_name": "PradatiusD/pFunk"
  },
  {
    "repo_name": "Safihre/cherrypy"
  },
  {
    "repo_name": "Sybil/PlayBotWeb"
  },
  {
    "repo_name": "TheDenys/Scripts"
  },
  {
    "repo_name": "VB-OnDuty/OnDuty"
  },
  {
    "repo_name": "VamCriss/JrmfLib"
  },
  {
    "repo_name": "Z2PackDev/Z2Pack"
  },
  {
    "repo_name": "ajkamel/dotfiles"
  },
  {
    "repo_name": "andering/overlay"
  },
  {
    "repo_name": "andrewherren/GEB"
  },
  {
    "repo_name": "atofigh/NHparser"
  },
  {
    "repo_name": "biggestbird/blog"
  },
  {
    "repo_name": "brinxmat/Perarne"
  },
  {
    "repo_name": "canek-pelaez/mlm"
  },
  {
    "repo_name": "ctz/brokenmalloc"
  },
  {
    "repo_name": "dato-code/how-to"
  },
  {
    "repo_name": "davidmogar/cucco"
  },
  {
    "repo_name": "dciccale/noflash"
  },
  {
    "repo_name": "dizko/trendyVidz"
  },
  {
    "repo_name": "dpsk/diablo3_api"
  },
  {
    "repo_name": "dshurt/OC-Proto1"
  },
  {
    "repo_name": "dummy-team/dummy"
  },
  {
    "repo_name": "dunse/try-it-out"
  },
  {
    "repo_name": "ebiggz/MixrElixr"
  },
  {
    "repo_name": "elibus/specinfra"
  },
  {
    "repo_name": "ericyue/deepcake"
  },
  {
    "repo_name": "faryon93/bmp2mif"
  },
  {
    "repo_name": "g-roma/Colliding"
  },
  {
    "repo_name": "garysims/goesmtp"
  },
  {
    "repo_name": "gitpbg/APCompSci"
  },
  {
    "repo_name": "gpoore/bespon_py"
  },
  {
    "repo_name": "h4tr3d/fx3-cmake"
  },
  {
    "repo_name": "heruan/bootstrap"
  },
  {
    "repo_name": "icanit/mangafeed"
  },
  {
    "repo_name": "j-bolger/symfony"
  },
  {
    "repo_name": "jahantech/Python"
  },
  {
    "repo_name": "johnty/libmapper"
  },
  {
    "repo_name": "kanon1109/bubble"
  },
  {
    "repo_name": "lighterio/thrust"
  },
  {
    "repo_name": "ljharb/jest-wrap"
  },
  {
    "repo_name": "lncd/Course-Data"
  },
  {
    "repo_name": "lnmnd/magnet.php"
  },
  {
    "repo_name": "lukasfirmyno/app"
  },
  {
    "repo_name": "lvshuang/agecart"
  },
  {
    "repo_name": "macquangson/kuix"
  },
  {
    "repo_name": "maugsburger/evie"
  },
  {
    "repo_name": "metalpapa/server"
  },
  {
    "repo_name": "mharrvic/SampVue"
  },
  {
    "repo_name": "mscribellito/BMI"
  },
  {
    "repo_name": "murekezi/Hygieia"
  },
  {
    "repo_name": "nZEDb/nZEDb_Docs"
  },
  {
    "repo_name": "nashj/Algorithms"
  },
  {
    "repo_name": "nccgroup/shocker"
  },
  {
    "repo_name": "nolith/breakcoin"
  },
  {
    "repo_name": "pepi55/math-in-c"
  },
  {
    "repo_name": "rickysahu/mpngen"
  },
  {
    "repo_name": "rmukras/ekda.org"
  },
  {
    "repo_name": "sunnyden/reactos"
  },
  {
    "repo_name": "tandasat/mylight"
  },
  {
    "repo_name": "tflidd/bookmarks"
  },
  {
    "repo_name": "wenber/scrollPic"
  },
  {
    "repo_name": "westphae/stratux"
  },
  {
    "repo_name": "xdggplus/MSpider"
  },
  {
    "repo_name": "yasukei/libstrut"
  },
  {
    "repo_name": "zephyriot/zephyr"
  },
  {
    "repo_name": "zhaogaolong/test"
  },
  {
    "repo_name": "AJPcodes/node-cal"
  },
  {
    "repo_name": "AutoVoid/Dotfiles"
  },
  {
    "repo_name": "BeaconCorp/beacon"
  },
  {
    "repo_name": "Detry322/git-psuh"
  },
  {
    "repo_name": "Indoqa/jar-in-jar"
  },
  {
    "repo_name": "JediCate/MiwokApp"
  },
  {
    "repo_name": "LostOfThought/MUP"
  },
  {
    "repo_name": "Mirek-Socha/gfxQt"
  },
  {
    "repo_name": "NicolaOrritos/sjl"
  },
  {
    "repo_name": "RedLucas/MotionUI"
  },
  {
    "repo_name": "SamLucyk/songbook"
  },
  {
    "repo_name": "Stavrakoudis/eucb"
  },
  {
    "repo_name": "TENDIGI/Starbucks"
  },
  {
    "repo_name": "ThatPerson/Unisim"
  },
  {
    "repo_name": "VDSoft/TheTVDBApi"
  },
  {
    "repo_name": "VShangxiao/v2ex-1"
  },
  {
    "repo_name": "Zakkazz/Elektrism"
  },
  {
    "repo_name": "ZkHaider/IrisData"
  },
  {
    "repo_name": "aiwuTech/hanziBoy"
  },
  {
    "repo_name": "amitav13/PicPload"
  },
  {
    "repo_name": "arnebech/Debounce"
  },
  {
    "repo_name": "blueskycoco/zcl-y"
  },
  {
    "repo_name": "bluschool/account"
  },
  {
    "repo_name": "bmihaylov/pycella"
  },
  {
    "repo_name": "boiawang/cheat.js"
  },
  {
    "repo_name": "bolt/FacebookLike"
  },
  {
    "repo_name": "cadrian/incentive"
  },
  {
    "repo_name": "craignicholson/P2"
  },
  {
    "repo_name": "crocodoyle/cbrain"
  },
  {
    "repo_name": "cryptix/go-tenten"
  },
  {
    "repo_name": "daveagp/websheets"
  },
  {
    "repo_name": "diggy106/leetcode"
  },
  {
    "repo_name": "dimitrieh/dhesign"
  },
  {
    "repo_name": "dsaves/dsaves-hdl"
  },
  {
    "repo_name": "easy-wi/developer"
  },
  {
    "repo_name": "exseed/exseed-cli"
  },
  {
    "repo_name": "gopikrish02/gkapp"
  },
  {
    "repo_name": "hex108/kubernetes"
  },
  {
    "repo_name": "hipgraphics/godot"
  },
  {
    "repo_name": "hjq/hjq.github.io"
  },
  {
    "repo_name": "iclosure/coolkits"
  },
  {
    "repo_name": "j4velin/IR-Remote"
  },
  {
    "repo_name": "jcfischer/TiStore"
  },
  {
    "repo_name": "jkgohlke/flatfile"
  },
  {
    "repo_name": "jleonard/radicals"
  },
  {
    "repo_name": "jmcarp/betfair.py"
  },
  {
    "repo_name": "joansmith/XChange"
  },
  {
    "repo_name": "jorgefilho/togglz"
  },
  {
    "repo_name": "kemoran/Pasantias"
  },
  {
    "repo_name": "leandrowd/batcher"
  },
  {
    "repo_name": "leesungju/Address"
  },
  {
    "repo_name": "leoh0/chef-client"
  },
  {
    "repo_name": "leotsai/dotimages"
  },
  {
    "repo_name": "li-yinan/whatever"
  },
  {
    "repo_name": "liadlow/LP-dialog"
  },
  {
    "repo_name": "littlebird/punter"
  },
  {
    "repo_name": "maltejk/provision"
  },
  {
    "repo_name": "mendhak/gpslogger"
  },
  {
    "repo_name": "mishan/thinksynth"
  },
  {
    "repo_name": "moonranger/breeze"
  },
  {
    "repo_name": "msosvi/flask-pyco"
  },
  {
    "repo_name": "nkgeorgiev/psilyp"
  },
  {
    "repo_name": "nprdm/jquery-pjax"
  },
  {
    "repo_name": "pewniak747/hipbot"
  },
  {
    "repo_name": "phusion/ucspi-tcp"
  },
  {
    "repo_name": "punitvara/ntppool"
  },
  {
    "repo_name": "pynamodb/PynamoDB"
  },
  {
    "repo_name": "rayallan/rayallan"
  },
  {
    "repo_name": "rfsfrn/railsready"
  },
  {
    "repo_name": "sc0Vu/vuethwallet"
  },
  {
    "repo_name": "scala/scala-swing"
  },
  {
    "repo_name": "smaludzi/mm-unify"
  },
  {
    "repo_name": "sphoebs/rockshell"
  },
  {
    "repo_name": "stathisg/blindify"
  },
  {
    "repo_name": "szzheng/Portfolio"
  },
  {
    "repo_name": "tbpgr/tbpgr_utils"
  },
  {
    "repo_name": "tcrossland/dotvim"
  },
  {
    "repo_name": "timotii48/Gravity"
  },
  {
    "repo_name": "tivec/rogueprison"
  },
  {
    "repo_name": "tsukhu/trace-demo"
  },
  {
    "repo_name": "ttakamura/sandbox"
  },
  {
    "repo_name": "urodoz/Chloe-i18n"
  },
  {
    "repo_name": "wangjun59/Masonry"
  },
  {
    "repo_name": "wsw0108/Windshaft"
  },
  {
    "repo_name": "xuwang/docker-dev"
  },
  {
    "repo_name": "yeoupooh/hannanum"
  },
  {
    "repo_name": "zhv/fluentbuilder"
  },
  {
    "repo_name": "ArturKami/helpdesk"
  },
  {
    "repo_name": "CalebAI/caleb-core"
  },
  {
    "repo_name": "Foldesk/foldesk_ui"
  },
  {
    "repo_name": "FriedBreakfast/tcc"
  },
  {
    "repo_name": "Gorbagzog/StageIAP"
  },
  {
    "repo_name": "ImaCoyote/hellogit"
  },
  {
    "repo_name": "Kevin6241/profolio"
  },
  {
    "repo_name": "LuyaoHuang/virtcov"
  },
  {
    "repo_name": "SBRK/react-gamepad"
  },
  {
    "repo_name": "Tanuj04/blog-codes"
  },
  {
    "repo_name": "ThePaavero/CodeGen"
  },
  {
    "repo_name": "Ulflander/lyonesse"
  },
  {
    "repo_name": "adde88/ManaToolkit"
  },
  {
    "repo_name": "aimingoo/continuer"
  },
  {
    "repo_name": "alejandromgk/Lunar"
  },
  {
    "repo_name": "carolshepherd/spsu"
  },
  {
    "repo_name": "cgiacomi/FluidLinq"
  },
  {
    "repo_name": "commonsense/divisi"
  },
  {
    "repo_name": "cracker64/Crackbot"
  },
  {
    "repo_name": "da3m0n/lunchOrders"
  },
  {
    "repo_name": "diegobqb/veboMaven"
  },
  {
    "repo_name": "dima-pu/afex-drone"
  },
  {
    "repo_name": "doakey3/Subsimport"
  },
  {
    "repo_name": "dodonator/numberGo"
  },
  {
    "repo_name": "drmonty/lrm-tomtom"
  },
  {
    "repo_name": "dulaccc/VFLToolbox"
  },
  {
    "repo_name": "flyerq/minesweeper"
  },
  {
    "repo_name": "geoquaidian/TecDEM"
  },
  {
    "repo_name": "gfetterman/zfparse"
  },
  {
    "repo_name": "gsmedley/translate"
  },
  {
    "repo_name": "gutenbergerp/gantt"
  },
  {
    "repo_name": "henryyan/snakeyaml"
  },
  {
    "repo_name": "hermanab/ryder2015"
  },
  {
    "repo_name": "isdev0/sel-9-test1"
  },
  {
    "repo_name": "jamesandres/enigma"
  },
  {
    "repo_name": "jasonday/printThis"
  },
  {
    "repo_name": "jseidl/pymodbuscli"
  },
  {
    "repo_name": "kanreisa/Hyperform"
  },
  {
    "repo_name": "kapoko/easy-fields"
  },
  {
    "repo_name": "kerenTeam/WEB_Chef"
  },
  {
    "repo_name": "kiwionly/AutoForce"
  },
  {
    "repo_name": "kvindasAB/css-test"
  },
  {
    "repo_name": "logicpie/oscarmike"
  },
  {
    "repo_name": "lucagtc/protocollo"
  },
  {
    "repo_name": "maljuboori91/pizza"
  },
  {
    "repo_name": "maxbuescher/canvas"
  },
  {
    "repo_name": "maxhoffmann/verlag"
  },
  {
    "repo_name": "micheljung/nocatch"
  },
  {
    "repo_name": "mitchty/pcre-light"
  },
  {
    "repo_name": "mmasson01/intranet"
  },
  {
    "repo_name": "mudhairless/mudcgi"
  },
  {
    "repo_name": "mvpel/clamav-devel"
  },
  {
    "repo_name": "nett55/caniusepypy"
  },
  {
    "repo_name": "noppoMan/socket.io"
  },
  {
    "repo_name": "northbright/keygen"
  },
  {
    "repo_name": "ogelami/ConnectApi"
  },
  {
    "repo_name": "philbooth/trier.js"
  },
  {
    "repo_name": "pplonski/keras2cpp"
  },
  {
    "repo_name": "ptrgags/supersonic"
  },
  {
    "repo_name": "quentinsf/uwsgiapp"
  },
  {
    "repo_name": "rneh/cs361ProjectB"
  },
  {
    "repo_name": "rover12421/Apktool"
  },
  {
    "repo_name": "samuelg/decorators"
  },
  {
    "repo_name": "spongecattle/house"
  },
  {
    "repo_name": "supernifty/biotool"
  },
  {
    "repo_name": "t4kq1995/mathsteps"
  },
  {
    "repo_name": "thebetabox/orthrus"
  },
  {
    "repo_name": "wp-plugins/wpbasis"
  },
  {
    "repo_name": "wsmoak/people_test"
  },
  {
    "repo_name": "xori/gamblers-dice"
  },
  {
    "repo_name": "zackharley/McHacks"
  },
  {
    "repo_name": "zimmski/monitoring"
  },
  {
    "repo_name": "zxteamorg/zxassist"
  },
  {
    "repo_name": "A-Lawrence/osticket"
  },
  {
    "repo_name": "BergSoft/python-epp"
  },
  {
    "repo_name": "CPtung/KARA_Android"
  },
  {
    "repo_name": "ComNets-Bremen/REMI"
  },
  {
    "repo_name": "Coretool/text2regex"
  },
  {
    "repo_name": "DMarugan/javascript"
  },
  {
    "repo_name": "Echrothy/I-dunno-JS"
  },
  {
    "repo_name": "Flickster42490/dage"
  },
  {
    "repo_name": "JCsAd2408/portfolio"
  },
  {
    "repo_name": "K0mpressor/progexam"
  },
  {
    "repo_name": "Kornelch/ChroTeMoVi"
  },
  {
    "repo_name": "L33m4n123/pdfMerger"
  },
  {
    "repo_name": "LeaVerou/multirange"
  },
  {
    "repo_name": "MatthewJWalls/Spiel"
  },
  {
    "repo_name": "Odrahcyr/amanda-xmp"
  },
  {
    "repo_name": "OmicsDI/ddi-web-app"
  },
  {
    "repo_name": "RobKuipers/domoticz"
  },
  {
    "repo_name": "SOSWEB-CH/protocall"
  },
  {
    "repo_name": "Shiiboun/GameOfLife"
  },
  {
    "repo_name": "Temikus/denim-theme"
  },
  {
    "repo_name": "adhearsion/ruby_jid"
  },
  {
    "repo_name": "alexlm78/OpenSchool"
  },
  {
    "repo_name": "ali-yilmaz/bypassfw"
  },
  {
    "repo_name": "amadoubakari/Rathel"
  },
  {
    "repo_name": "andreyloktev/WinVFS"
  },
  {
    "repo_name": "andyftw/image-faker"
  },
  {
    "repo_name": "anih/django-getpaid"
  },
  {
    "repo_name": "awesomethomas/gemrb"
  },
  {
    "repo_name": "azizdhaifullah/aziz"
  },
  {
    "repo_name": "bgeneva/TechModule1"
  },
  {
    "repo_name": "bmcfee/pyrubberband"
  },
  {
    "repo_name": "bpoplauschi/BPForms"
  },
  {
    "repo_name": "brain-murphy/Bitter"
  },
  {
    "repo_name": "chrisgreg/tagscrape"
  },
  {
    "repo_name": "codingjoe/django-cc"
  },
  {
    "repo_name": "corbt/homebrew-cask"
  },
  {
    "repo_name": "cybergrouch/Coupool"
  },
  {
    "repo_name": "danielsdeleo/qusion"
  },
  {
    "repo_name": "danyshaanan/gist.im"
  },
  {
    "repo_name": "deefactorial/omlets"
  },
  {
    "repo_name": "delineas/IntroSilex"
  },
  {
    "repo_name": "devakdo/codemontage"
  },
  {
    "repo_name": "duemunk/iCloudStore"
  },
  {
    "repo_name": "ebaratch/MelanomaCA"
  },
  {
    "repo_name": "edsadr/node-uinames"
  },
  {
    "repo_name": "emb-team/410-golang"
  },
  {
    "repo_name": "er4z0r/fwknob-proxy"
  },
  {
    "repo_name": "ethilesen/NodeSapJS"
  },
  {
    "repo_name": "evil-e/sdb-explorer"
  },
  {
    "repo_name": "fabric8io/gofabric8"
  },
  {
    "repo_name": "farisnasution/karen"
  },
  {
    "repo_name": "flatworld/core-plot"
  },
  {
    "repo_name": "galenhz/micropython"
  },
  {
    "repo_name": "gmarciani/gmarciani"
  },
  {
    "repo_name": "greenc/CookieMaster"
  },
  {
    "repo_name": "hholzgra/maposmatic"
  },
  {
    "repo_name": "intuitivcloud/putty"
  },
  {
    "repo_name": "ivoba/sfFeed2Plugin"
  },
  {
    "repo_name": "jmhsi/justin_tinker"
  },
  {
    "repo_name": "karlitxo/spree_i18n"
  },
  {
    "repo_name": "kevinwojo/templates"
  },
  {
    "repo_name": "koesie10/realm-pojo"
  },
  {
    "repo_name": "krinkinmu/aufs-temp"
  },
  {
    "repo_name": "kwrooijen/LazyVault"
  },
  {
    "repo_name": "kylesferrazza/wmmtc"
  },
  {
    "repo_name": "lawrence-yu/okaidia"
  },
  {
    "repo_name": "lorcanmooney/roslyn"
  },
  {
    "repo_name": "lorcanmooney/roslyn"
  },
  {
    "repo_name": "marcosg29/Asteroids"
  },
  {
    "repo_name": "matthewrobb/mber.js"
  },
  {
    "repo_name": "maximka1221/2D-Game"
  },
  {
    "repo_name": "nerro/docker-images"
  },
  {
    "repo_name": "nex3/perspective-el"
  },
  {
    "repo_name": "nikhil93uf/kvm-kmod"
  },
  {
    "repo_name": "npgall/mobility-rpc"
  },
  {
    "repo_name": "payman81/je-voucher"
  },
  {
    "repo_name": "pepijnkokke/Dep2Con"
  },
  {
    "repo_name": "pinax/django-mailer"
  },
  {
    "repo_name": "reinsle/thw-heizung"
  },
  {
    "repo_name": "rubenhortas/aliases"
  },
  {
    "repo_name": "schiermike/syncarus"
  },
  {
    "repo_name": "sdockray/ai-commune"
  },
  {
    "repo_name": "sequenceiq/cbdproxy"
  },
  {
    "repo_name": "servo/doc.servo.org"
  },
  {
    "repo_name": "sgproduce/FarmPlans"
  },
  {
    "repo_name": "shamsher31/goistext"
  },
  {
    "repo_name": "shoukaiseki/blogdoc"
  },
  {
    "repo_name": "skiwi2/OGamePlanner"
  },
  {
    "repo_name": "sportsy/sportsstats"
  },
  {
    "repo_name": "stuconnolly/NetDemo"
  },
  {
    "repo_name": "svetlai/Battleships"
  },
  {
    "repo_name": "techgaun/ex_mustang"
  },
  {
    "repo_name": "timhok/CheckWinRaid"
  },
  {
    "repo_name": "tsaikd/docker-noip2"
  },
  {
    "repo_name": "ujas123/icd_roffing"
  },
  {
    "repo_name": "vietpn/ghost-nodejs"
  },
  {
    "repo_name": "vritant/python-rhsm"
  },
  {
    "repo_name": "wncnho18/ProjectG-D"
  },
  {
    "repo_name": "01org/thermal_daemon"
  },
  {
    "repo_name": "Adriang71/yelp_clone"
  },
  {
    "repo_name": "CG-F15-26-Rutgers/A4"
  },
  {
    "repo_name": "DisruptiveLabs/nacha"
  },
  {
    "repo_name": "EyuelAbebe/sentiment"
  },
  {
    "repo_name": "GCY/Heartbeat-Sensor"
  },
  {
    "repo_name": "GTmmiller/bankinator"
  },
  {
    "repo_name": "JCherryhomes/ng-idle"
  },
  {
    "repo_name": "Kunstmaan/i18n-swift"
  },
  {
    "repo_name": "Leaflet/Leaflet.heat"
  },
  {
    "repo_name": "Milstein/twittercoin"
  },
  {
    "repo_name": "ORNL-Fusion/kineticj"
  },
  {
    "repo_name": "Open-GTO/weaponskill"
  },
  {
    "repo_name": "Ritzvillcoin/inncoin"
  },
  {
    "repo_name": "Spinlocks/99Problems"
  },
  {
    "repo_name": "Tigge/platinumshrimp"
  },
  {
    "repo_name": "TimurKastemirov/skb3"
  },
  {
    "repo_name": "Tominator001/GitCode"
  },
  {
    "repo_name": "UpThemes/WP-Facebook"
  },
  {
    "repo_name": "VividCortex/robustly"
  },
  {
    "repo_name": "VtoVote/v-initiative"
  },
  {
    "repo_name": "aditgoyal19/Swingejs"
  },
  {
    "repo_name": "afrogeek/SharpNative"
  },
  {
    "repo_name": "ajamesl/VectorTarget"
  },
  {
    "repo_name": "ajlopez/SimpleSudoku"
  },
  {
    "repo_name": "akainth/phpAdminTest"
  },
  {
    "repo_name": "amprog/wordpress-seo"
  },
  {
    "repo_name": "anilmaurya/portfolio"
  },
  {
    "repo_name": "anushbmx/PHPDateTime"
  },
  {
    "repo_name": "aspitz/ZCircleButton"
  },
  {
    "repo_name": "c4pt0r/protoc-gen-go"
  },
  {
    "repo_name": "catatsuy/bench_write"
  },
  {
    "repo_name": "ccworld1000/CCSQLite"
  },
  {
    "repo_name": "chetan/bixby-manager"
  },
  {
    "repo_name": "cloudarts/transmit64"
  },
  {
    "repo_name": "cloudpassage/don-bot"
  },
  {
    "repo_name": "cmhc/shadowsocks-php"
  },
  {
    "repo_name": "danielkasza/fracking"
  },
  {
    "repo_name": "davidcs1708/proyecto"
  },
  {
    "repo_name": "dball/data_relations"
  },
  {
    "repo_name": "dicehead3/Kaartenbak"
  },
  {
    "repo_name": "ellisio/jquery.phone"
  },
  {
    "repo_name": "ericstevens27/ang-rm"
  },
  {
    "repo_name": "euskadi31/glide-objc"
  },
  {
    "repo_name": "f8al/fuzzy-guacamole"
  },
  {
    "repo_name": "freecode/FVB-Modules"
  },
  {
    "repo_name": "gandm/language-babel"
  },
  {
    "repo_name": "giacomelli/TheOthers"
  },
  {
    "repo_name": "gitronald/demotables"
  },
  {
    "repo_name": "grzegorz7/spock-copy"
  },
  {
    "repo_name": "guohaoxu/react-demos"
  },
  {
    "repo_name": "heLomaN/contentmaker"
  },
  {
    "repo_name": "helinjiang/pro-mocha"
  },
  {
    "repo_name": "imguttman/mypomodoro"
  },
  {
    "repo_name": "imprazaguy/my-config"
  },
  {
    "repo_name": "imsaar/zainab-school"
  },
  {
    "repo_name": "ityangs/MultiProcess"
  },
  {
    "repo_name": "jamesrwhite/minicron"
  },
  {
    "repo_name": "jarkyll/angular-demo"
  },
  {
    "repo_name": "jasperschulz/routems"
  },
  {
    "repo_name": "jazzhubgit1/0630-gh1"
  },
  {
    "repo_name": "jeremy-bernon/Lilith"
  },
  {
    "repo_name": "josephwegner/pushpop"
  },
  {
    "repo_name": "kavyasukumar/onthego"
  },
  {
    "repo_name": "kidd1118/GradientPie"
  },
  {
    "repo_name": "kriserickson/KrisMVC"
  },
  {
    "repo_name": "ltog/robocopy-backup"
  },
  {
    "repo_name": "mayflower/puppet-php"
  },
  {
    "repo_name": "meriac/openbeacon-ng"
  },
  {
    "repo_name": "micaelsouza/tiled-js"
  },
  {
    "repo_name": "monkii-dev/neocortex"
  },
  {
    "repo_name": "muccnyik/hello-world"
  },
  {
    "repo_name": "mwolting/pipeline-rs"
  },
  {
    "repo_name": "nanoporetech/lamprey"
  },
  {
    "repo_name": "nfuller52/tf-wp-site"
  },
  {
    "repo_name": "ninjabunny/KodeNames"
  },
  {
    "repo_name": "nubivagant/lcc-guide"
  },
  {
    "repo_name": "orsteve77/ecommerce1"
  },
  {
    "repo_name": "overthink/vimclojure"
  },
  {
    "repo_name": "phildow/ZFTokenField"
  },
  {
    "repo_name": "pvpatriota/monitoria"
  },
  {
    "repo_name": "redien/Ludum-Dare-20"
  },
  {
    "repo_name": "retroburst/IRWatcher"
  },
  {
    "repo_name": "rmarmier/gitworkshop"
  },
  {
    "repo_name": "rmvanhees/nadc_tools"
  },
  {
    "repo_name": "rosogon/unified-paas"
  },
  {
    "repo_name": "rozentill/PatchMatch"
  },
  {
    "repo_name": "rwieber/SQLiteDumper"
  },
  {
    "repo_name": "samtny/photos-deploy"
  },
  {
    "repo_name": "sharemind-sdk/stdlib"
  },
  {
    "repo_name": "sncn-private/PCL-OCL"
  },
  {
    "repo_name": "stevecrozz/ruby-saml"
  },
  {
    "repo_name": "swys/Get-O365Session"
  },
  {
    "repo_name": "tavvy/GPM-Playlister"
  },
  {
    "repo_name": "tdao14/JavaAlgorithm"
  },
  {
    "repo_name": "thumby/flask-thumbor"
  },
  {
    "repo_name": "tibogens/OpenThreads"
  },
  {
    "repo_name": "tim-baker/embedded-c"
  },
  {
    "repo_name": "tommypoernomo/vocabs"
  },
  {
    "repo_name": "tortib/Equinox-Light"
  },
  {
    "repo_name": "vikassatpute/tuition"
  },
  {
    "repo_name": "wilsonge/twitter-api"
  },
  {
    "repo_name": "wspeirs/rust-compare"
  },
  {
    "repo_name": "yyanasun/java_course"
  },
  {
    "repo_name": "zenefits/ember-model"
  },
  {
    "repo_name": "zhuchaowe/ModelCoder"
  },
  {
    "repo_name": "2bithacker/shirtsaver"
  },
  {
    "repo_name": "8th713/ExpandFootNote"
  },
  {
    "repo_name": "Arpapiemonte/openoise"
  },
  {
    "repo_name": "AtomyChan/pybilliards"
  },
  {
    "repo_name": "CSSZiegler/HelloWorld"
  },
  {
    "repo_name": "EvanMessinger/make.js"
  },
  {
    "repo_name": "Joisar/Python-Scripts"
  },
  {
    "repo_name": "KevinMcHugh/femtotest"
  },
  {
    "repo_name": "Khan/react-components"
  },
  {
    "repo_name": "Liukunpro/coolweather"
  },
  {
    "repo_name": "MySmallCase/CodingNet"
  },
  {
    "repo_name": "RuyiLi/endless-undyne"
  },
  {
    "repo_name": "Skippeh/Oxide-Plugins"
  },
  {
    "repo_name": "X-DataInitiative/tick"
  },
  {
    "repo_name": "abhinavmoudgil95/root"
  },
  {
    "repo_name": "ahbou/MICountryPicker"
  },
  {
    "repo_name": "alekfestekjian/easyAI"
  },
  {
    "repo_name": "android-tester1/test2"
  },
  {
    "repo_name": "angrycans/LrestServer"
  },
  {
    "repo_name": "apostopher/smart-chat"
  },
  {
    "repo_name": "asyncore/DeepBeliever"
  },
  {
    "repo_name": "bibendovsky/lgvidsubs"
  },
  {
    "repo_name": "chjj/Live-Stylesheets"
  },
  {
    "repo_name": "chuva-io/server-chuva"
  },
  {
    "repo_name": "coolrankit/coolrankit"
  },
  {
    "repo_name": "craftytrickster/servo"
  },
  {
    "repo_name": "csluder/Linux-drivers"
  },
  {
    "repo_name": "cvrlebg/diwaneePlayer"
  },
  {
    "repo_name": "dekujs/assert-element"
  },
  {
    "repo_name": "demulab/face_detector"
  },
  {
    "repo_name": "deviceone/do_ListView"
  },
  {
    "repo_name": "dfdeshom/nim_log_perf"
  },
  {
    "repo_name": "dillonforrest/startup"
  },
  {
    "repo_name": "dreadworks/college-cg"
  },
  {
    "repo_name": "eliasp/updatenotifier"
  },
  {
    "repo_name": "essentim/api-examples"
  },
  {
    "repo_name": "euangoddard/xmas-2015"
  },
  {
    "repo_name": "fengshao0907/astyanax"
  },
  {
    "repo_name": "gang2319/CoolWheather"
  },
  {
    "repo_name": "gneisefr/javaworkshop"
  },
  {
    "repo_name": "harictengazel/mariadb"
  },
  {
    "repo_name": "hotchemi/Android-Rate"
  },
  {
    "repo_name": "hryptr/TestGitProject"
  },
  {
    "repo_name": "hughsaunders/keystone"
  },
  {
    "repo_name": "huipengly/chat_server"
  },
  {
    "repo_name": "icleversoft/rnotifier"
  },
  {
    "repo_name": "ideaworld/BioDesigner"
  },
  {
    "repo_name": "jamesg1/react-project"
  },
  {
    "repo_name": "jhaker/nodejs-msbuild"
  },
  {
    "repo_name": "jo-c-2017/DS_Projects"
  },
  {
    "repo_name": "kirankoduru/changelog"
  },
  {
    "repo_name": "magezone/testimonials"
  },
  {
    "repo_name": "marciniwanicki/DFDiff"
  },
  {
    "repo_name": "mile-janev/kladilnica"
  },
  {
    "repo_name": "mironal/QBImagePicker"
  },
  {
    "repo_name": "mukel/mukel.github.io"
  },
  {
    "repo_name": "mvmike/min-cal-widget"
  },
  {
    "repo_name": "mw-ferretti/e-braille"
  },
  {
    "repo_name": "nhostad/github-basics"
  },
  {
    "repo_name": "onetapbeyond/fluent-r"
  },
  {
    "repo_name": "onyx-intl/ak98_kernel"
  },
  {
    "repo_name": "openplans/streetscore"
  },
  {
    "repo_name": "p-ja/javabeginner2017"
  },
  {
    "repo_name": "paralin/EVESystemJSON"
  },
  {
    "repo_name": "pboueke/presentations"
  },
  {
    "repo_name": "praisethemoon/berserk"
  },
  {
    "repo_name": "pstrinkle/sql2pymongo"
  },
  {
    "repo_name": "quuxlabs/goodiff-core"
  },
  {
    "repo_name": "ravi2kr6/otmonitoring"
  },
  {
    "repo_name": "rubasov/opensub-utils"
  },
  {
    "repo_name": "runtimerevolution/fog"
  },
  {
    "repo_name": "sendgrid-ops/rabbitmq"
  },
  {
    "repo_name": "sio-iago/sioframework"
  },
  {
    "repo_name": "sixears/rainbow-lines"
  },
  {
    "repo_name": "sook/drumon_framework"
  },
  {
    "repo_name": "spatialhast/gpstracks"
  },
  {
    "repo_name": "stefscorner/couchtest"
  },
  {
    "repo_name": "sunqinwpu/java-common"
  },
  {
    "repo_name": "timlinux/osm-reporter"
  },
  {
    "repo_name": "tlevine/strataeu-2012"
  },
  {
    "repo_name": "trickl/trickl-crawler"
  },
  {
    "repo_name": "trinhthinhhp/nukeviet"
  },
  {
    "repo_name": "voux-io/track-digests"
  },
  {
    "repo_name": "vshn/puppet-in-docker"
  },
  {
    "repo_name": "zambonin/UFSC-INE5415"
  },
  {
    "repo_name": "Backman/Dreamhackathon"
  },
  {
    "repo_name": "Bergrebell/phonegapapp"
  },
  {
    "repo_name": "DanHouk/LocationFlickr"
  },
  {
    "repo_name": "EventaxhlTeam/Bejarasu"
  },
  {
    "repo_name": "Fariah/jracko-zakazaka"
  },
  {
    "repo_name": "Hussain1993/SpamServer"
  },
  {
    "repo_name": "IcecaveStudios/dialekt"
  },
  {
    "repo_name": "KamyarNemati/TicTacToe"
  },
  {
    "repo_name": "KoryNunn/gaffa-heading"
  },
  {
    "repo_name": "LEDS/millennium-falcon"
  },
  {
    "repo_name": "LetosTech/Wes-Painting"
  },
  {
    "repo_name": "Marcocanc/TiIconicFont"
  },
  {
    "repo_name": "Nicholas11/Technicraft"
  },
  {
    "repo_name": "ONCHoldings/graft-auth"
  },
  {
    "repo_name": "Stilg4r/Alias-Diceware"
  },
  {
    "repo_name": "UniversalAvenue/reacon"
  },
  {
    "repo_name": "adilraja/SensorNetwork"
  },
  {
    "repo_name": "alfonsojon/cryptomeria"
  },
  {
    "repo_name": "azurelogic/XdtExtended"
  },
  {
    "repo_name": "chikoski/wasm-asm-demo"
  },
  {
    "repo_name": "chunlizh/SmartStoreNET"
  },
  {
    "repo_name": "dbarajassolano/gsl_int"
  },
  {
    "repo_name": "devinmiller/ESFeatures"
  },
  {
    "repo_name": "elZati/AS3935_MOD-1016"
  },
  {
    "repo_name": "etna-alternance/castor"
  },
  {
    "repo_name": "fidomax/openscada-kium"
  },
  {
    "repo_name": "flaviendelangle/resume"
  },
  {
    "repo_name": "frank-deng/retro-works"
  },
  {
    "repo_name": "google/cauliflowervest"
  },
  {
    "repo_name": "hxsylzpf/hxsylzpf.html"
  },
  {
    "repo_name": "ileri/http-header-link"
  },
  {
    "repo_name": "imanhodjaev/monitoring"
  },
  {
    "repo_name": "infil00p/PhoneGapTango"
  },
  {
    "repo_name": "itsapi/github-listener"
  },
  {
    "repo_name": "jakekniight/Salford-SU"
  },
  {
    "repo_name": "jamesacampbell/jiminal"
  },
  {
    "repo_name": "jansen03/Final-Project"
  },
  {
    "repo_name": "jaschaephraim/lrserver"
  },
  {
    "repo_name": "justin1121/rusty-redis"
  },
  {
    "repo_name": "kavaro/es6-css-modules"
  },
  {
    "repo_name": "kbiva/LPC810_Nokia_LCD"
  },
  {
    "repo_name": "kedarbramhe/py-adxl345"
  },
  {
    "repo_name": "kimmel/apt-mirror-fork"
  },
  {
    "repo_name": "lab46/git-diff-summary"
  },
  {
    "repo_name": "leverdeterre/iAppInfos"
  },
  {
    "repo_name": "lopezconsu/CrowdDesign"
  },
  {
    "repo_name": "lumierecyril/socket.io"
  },
  {
    "repo_name": "mardix/flask-recaptcha"
  },
  {
    "repo_name": "mastahyeti/SoftU2FTool"
  },
  {
    "repo_name": "michael-milette/moodle"
  },
  {
    "repo_name": "michaellions/comboGrid"
  },
  {
    "repo_name": "mm-ocampo/phonegapdemo"
  },
  {
    "repo_name": "moneeb777/wifi-grabber"
  },
  {
    "repo_name": "p0o/React-Video-Player"
  },
  {
    "repo_name": "pat-thomas/breadcrumbs"
  },
  {
    "repo_name": "piorpua/AndroidBaseLib"
  },
  {
    "repo_name": "pokerov/DesignPatterns"
  },
  {
    "repo_name": "rodrigomuniz/ui-matter"
  },
  {
    "repo_name": "rypcarr/terraform-demo"
  },
  {
    "repo_name": "sagitarius29/sgFactura"
  },
  {
    "repo_name": "shitanshupatil/Caravan"
  },
  {
    "repo_name": "simon-pham/hello-world"
  },
  {
    "repo_name": "spolnik/mongodb_sample"
  },
  {
    "repo_name": "stealthly/docker-spark"
  },
  {
    "repo_name": "strabsquad/loadingtime"
  },
  {
    "repo_name": "tedlodydesign2014/lava"
  },
  {
    "repo_name": "tempbottle/qrcode-rust"
  },
  {
    "repo_name": "tu-software-studio/VVV"
  },
  {
    "repo_name": "vellotis/strong-params"
  },
  {
    "repo_name": "wsams/SimpleImageShare"
  },
  {
    "repo_name": "wtsarchive/Rocket.Chat"
  },
  {
    "repo_name": "xsteadfastx/Emby.Build"
  },
  {
    "repo_name": "yassineb/remote-backup"
  },
  {
    "repo_name": "yzrobot/pose_publisher"
  },
  {
    "repo_name": "zack9433/F2E_Must_Know"
  },
  {
    "repo_name": "Advaya-Labs/moreSAILnet"
  },
  {
    "repo_name": "Ashyoo/Ashyoo.github.io"
  },
  {
    "repo_name": "BCsl/hellocsl.github.io"
  },
  {
    "repo_name": "ChiralBehaviors/steward"
  },
  {
    "repo_name": "GoodArtistsCopy/gonzole"
  },
  {
    "repo_name": "JacksonTian/koa-forward"
  },
  {
    "repo_name": "KlotzAndrew/rspec-rails"
  },
  {
    "repo_name": "MPRedEagle/ModPe-Script"
  },
  {
    "repo_name": "MZT19901006/tt510083772"
  },
  {
    "repo_name": "Medeocree21/My-reposity"
  },
  {
    "repo_name": "MrVibe/bp-profile-cover"
  },
  {
    "repo_name": "Palmaswell/Task-Tracker"
  },
  {
    "repo_name": "PearlVentures/Crux-apps"
  },
  {
    "repo_name": "SP7-Ritmare/O-MTemplate"
  },
  {
    "repo_name": "Sup3r-Us3r/Arch-Install"
  },
  {
    "repo_name": "TedChenNZ/TedChenNZ-Web"
  },
  {
    "repo_name": "Xianguang-Zhou/light-dd"
  },
  {
    "repo_name": "acatton/OpenPGP-Haskell"
  },
  {
    "repo_name": "acl2018/acl2018-website"
  },
  {
    "repo_name": "alexpagnoni/mimemaillib"
  },
  {
    "repo_name": "andersonsilvade/5script"
  },
  {
    "repo_name": "anzap/ActsAsCommentable"
  },
  {
    "repo_name": "basicallydan/skifree.js"
  },
  {
    "repo_name": "bbuchalter/python_koans"
  },
  {
    "repo_name": "braveulysses/tumblr-api"
  },
  {
    "repo_name": "brethash/magmi-datapump"
  },
  {
    "repo_name": "canidae/GoFlyAutoLogger"
  },
  {
    "repo_name": "carlos-wong/l430_kernel"
  },
  {
    "repo_name": "cleandart/clean_backend"
  },
  {
    "repo_name": "curran/migrantDeathsVis"
  },
  {
    "repo_name": "devage/usedbooks-search"
  },
  {
    "repo_name": "digib0y/DemoHarfbuzzApp"
  },
  {
    "repo_name": "dmitris/yuiconftalk2012"
  },
  {
    "repo_name": "dmr/elasticsearch_tests"
  },
  {
    "repo_name": "duyngha/clicksold-addon"
  },
  {
    "repo_name": "dwyl/definition-of-done"
  },
  {
    "repo_name": "dylanchernick/ghostblog"
  },
  {
    "repo_name": "estratos/Dineromail-PHP"
  },
  {
    "repo_name": "flapjack/flapjackfeeder"
  },
  {
    "repo_name": "freebroccolo/machine.rs"
  },
  {
    "repo_name": "gizmo385/TheFourNations"
  },
  {
    "repo_name": "gjtorikian/commonmarker"
  },
  {
    "repo_name": "grazerjink/PhatHanhSach"
  },
  {
    "repo_name": "grovelabs/react-i13n-ga"
  },
  {
    "repo_name": "hamesetawa/EDMGenerator"
  },
  {
    "repo_name": "hubwub/hubwub.github.io"
  },
  {
    "repo_name": "humbertolima/CharpTrack"
  },
  {
    "repo_name": "infosec-o4it/inventario"
  },
  {
    "repo_name": "jackocnr/intl-tel-input"
  },
  {
    "repo_name": "jamesotron/vivid_png.ex"
  },
  {
    "repo_name": "joeyates/gist_directory"
  },
  {
    "repo_name": "johnotander/generator-p"
  },
  {
    "repo_name": "joshuapaling/browserlog"
  },
  {
    "repo_name": "juniwang/JavaHelloWorld"
  },
  {
    "repo_name": "k15z/CsEdu-3-Perceptron"
  },
  {
    "repo_name": "klenovic/nucleos-newlib"
  },
  {
    "repo_name": "laem/static-server-hook"
  },
  {
    "repo_name": "lauramcastro/webui-test"
  },
  {
    "repo_name": "lion123dev/Lionlib-HAXE"
  },
  {
    "repo_name": "lukepur/wt-service-auth"
  },
  {
    "repo_name": "manybots/manybots-gmail"
  },
  {
    "repo_name": "marshallhumble/Sunlight"
  },
  {
    "repo_name": "matekm/matekm.github.io"
  },
  {
    "repo_name": "menski/minipcs-cookbook"
  },
  {
    "repo_name": "moongift/NCMBiOSFaceook"
  },
  {
    "repo_name": "mutagendev/lemp-formula"
  },
  {
    "repo_name": "mzhaom/sysadmin-toolkit"
  },
  {
    "repo_name": "neovintage/zoho_invoice"
  },
  {
    "repo_name": "nfqde/entitylist-bundle"
  },
  {
    "repo_name": "nicholasbair/dogtracker"
  },
  {
    "repo_name": "philipdnichols/chat-app"
  },
  {
    "repo_name": "pocketly/andy-vigilante"
  },
  {
    "repo_name": "qiuyuanyang/hello-world"
  },
  {
    "repo_name": "quentint/tkwk-font-size"
  },
  {
    "repo_name": "rachelweissman/Bloctime"
  },
  {
    "repo_name": "radnit/radnit.github.io"
  },
  {
    "repo_name": "rafapzz/learning-python"
  },
  {
    "repo_name": "ramesh-dev/JMandrillApi"
  },
  {
    "repo_name": "rejectedsoftware/vibe.d"
  },
  {
    "repo_name": "rocketengineio/M3U2Emby"
  },
  {
    "repo_name": "romovs/xula-lib-verilog"
  },
  {
    "repo_name": "scherma/hfs-plus-reader"
  },
  {
    "repo_name": "sdgdsffdsfff/nginx-.tar"
  },
  {
    "repo_name": "sebsonic2o/thunder-talk"
  },
  {
    "repo_name": "section6nz/sqljdbc-osgi"
  },
  {
    "repo_name": "shanham/Nano_Paint_Demo"
  },
  {
    "repo_name": "startupstorm/StormTalks"
  },
  {
    "repo_name": "tiagoschreiner/pageRank"
  },
  {
    "repo_name": "tokuda109/flask-docs-ja"
  },
  {
    "repo_name": "vmasciotta/StoreLocator"
  },
  {
    "repo_name": "waynecz/vue-img-inputer"
  },
  {
    "repo_name": "waynetunmyint/football2"
  },
  {
    "repo_name": "ydkn/rails-menu-manager"
  },
  {
    "repo_name": "zeinebchelly/FuzzyLogic"
  },
  {
    "repo_name": "AndrewRademacher/drifter"
  },
  {
    "repo_name": "Archomeda/TS3-GW2-plugin"
  },
  {
    "repo_name": "Gattermeier/nodejs-virus"
  },
  {
    "repo_name": "IvanGaravito/dnpAnalyzer"
  },
  {
    "repo_name": "JScott/terminal-announce"
  },
  {
    "repo_name": "Kizr/darkest_resolve_bot"
  },
  {
    "repo_name": "NateJacobs/Jacobs-Family"
  },
  {
    "repo_name": "Nozdi/webpage-similarity"
  },
  {
    "repo_name": "OpenGene/FusionDirect.jl"
  },
  {
    "repo_name": "Pshrub/office-poll-topic"
  },
  {
    "repo_name": "Team997Coders/Cynder2015"
  },
  {
    "repo_name": "Tradeshift/spiritual-edb"
  },
  {
    "repo_name": "UCL-RITS/licenselogparse"
  },
  {
    "repo_name": "VarunJoshi/NodeACSSample"
  },
  {
    "repo_name": "WarmongeR1/python-wialon"
  },
  {
    "repo_name": "algorithmiaio/dev-center"
  },
  {
    "repo_name": "beli-sk/iptables-m4-init"
  },
  {
    "repo_name": "budnik/dokku-solr-plugin"
  },
  {
    "repo_name": "callen333/WindowsIoTCore"
  },
  {
    "repo_name": "casperdre/WIP-Congig.cpp"
  },
  {
    "repo_name": "catinwarmhands/Randogram"
  },
  {
    "repo_name": "dino-poblete/aestrea-www"
  },
  {
    "repo_name": "dmbarbour/haskell-vcache"
  },
  {
    "repo_name": "ethankruse/kepler_orrery"
  },
  {
    "repo_name": "gabrielflorit/livecoding"
  },
  {
    "repo_name": "gaqzi/spotify-controller"
  },
  {
    "repo_name": "gauravtiwari/goldiloader"
  },
  {
    "repo_name": "gongo/anything-vim-hacks"
  },
  {
    "repo_name": "hashivim/vim-ottoproject"
  },
  {
    "repo_name": "ingo-budde/mpdclient-sdl"
  },
  {
    "repo_name": "iunderwood/uhq_geolocate"
  },
  {
    "repo_name": "jdwittenauer/insight-net"
  },
  {
    "repo_name": "juanplopes/algorithms.js"
  },
  {
    "repo_name": "justsoso8/linux-2.6.32.9"
  },
  {
    "repo_name": "kevmoo/shelf_static.dart"
  },
  {
    "repo_name": "krmaxwell/insult-creator"
  },
  {
    "repo_name": "lipisha/lipisha-node-sdk"
  },
  {
    "repo_name": "lynnchurch/CocosLearning"
  },
  {
    "repo_name": "masilver99/CommandRunner"
  },
  {
    "repo_name": "matthew-brett/wheels2dmg"
  },
  {
    "repo_name": "mdmsoft/yii2-ar-relation"
  },
  {
    "repo_name": "michaelschade/rww-author"
  },
  {
    "repo_name": "mikedhart/ContentControl"
  },
  {
    "repo_name": "mkaraki/IPAddressManager"
  },
  {
    "repo_name": "moonyl/sunshineFollowing"
  },
  {
    "repo_name": "nicopaez/javacollections"
  },
  {
    "repo_name": "olksdr/async-http-client"
  },
  {
    "repo_name": "omesquita/curso-php-free"
  },
  {
    "repo_name": "phamdacloc/BlinkingLabel"
  },
  {
    "repo_name": "ravenjohn/learning-webgl"
  },
  {
    "repo_name": "ray-curran/phase-0-gps-1"
  },
  {
    "repo_name": "rb-cohen/js-input-slider"
  },
  {
    "repo_name": "rfennell/StyleCopCmdLine"
  },
  {
    "repo_name": "roshanr95/TimeExtensions"
  },
  {
    "repo_name": "rwaldron/traceur-todomvc"
  },
  {
    "repo_name": "sanemat/hubot-lets-party"
  },
  {
    "repo_name": "saschpe/BirthdayCalendar"
  },
  {
    "repo_name": "sheryiu/CSS-Icon-Builder"
  },
  {
    "repo_name": "shiguanglideqi/node_test"
  },
  {
    "repo_name": "smile-community/BWFtools"
  },
  {
    "repo_name": "telusdigital/ansible-php"
  },
  {
    "repo_name": "thorstadt/grails-clojure"
  },
  {
    "repo_name": "vunvulear/IoTHomeProject"
  },
  {
    "repo_name": "yishuiliunian/StyleSheet"
  },
  {
    "repo_name": "zabawaba99/docker-gradle"
  },
  {
    "repo_name": "zend-modules/site-config"
  },
  {
    "repo_name": "0xE0F/git-flow-completion"
  },
  {
    "repo_name": "AngelLomeli/Project-Euler"
  },
  {
    "repo_name": "Azollas/org.azolla.p.2048"
  },
  {
    "repo_name": "CharlesJQuarra/Tensor-AIS"
  },
  {
    "repo_name": "Commonjava/webdav-handler"
  },
  {
    "repo_name": "CrazyDD/CrazyDD.github.io"
  },
  {
    "repo_name": "Dronolab/antenna-tracking"
  },
  {
    "repo_name": "FoxLang/foxlang.github.io"
  },
  {
    "repo_name": "GreatDevelopers/SageLaTeX"
  },
  {
    "repo_name": "Heptoxide/COBRA-HybridDev"
  },
  {
    "repo_name": "MachinesWhoLearn/lectures"
  },
  {
    "repo_name": "MrNoahz/MrNoahz.github.io"
  },
  {
    "repo_name": "PedestrianSean/FringeData"
  },
  {
    "repo_name": "PistonDevelopers/xpath-rs"
  },
  {
    "repo_name": "SilMOON/silmoon.github.io"
  },
  {
    "repo_name": "StefanoTavonatti/SvgToPNG"
  },
  {
    "repo_name": "ThePooN/RightClickSpammer"
  },
  {
    "repo_name": "TonyWijaya/SistemAkademik"
  },
  {
    "repo_name": "Trott/a-talk-with-no-name"
  },
  {
    "repo_name": "UfSoft/trac-google-search"
  },
  {
    "repo_name": "WCRSyyc/servo-calibration"
  },
  {
    "repo_name": "X0nic/automagic-wordpress"
  },
  {
    "repo_name": "YColander/build-essential"
  },
  {
    "repo_name": "aayushchugh07/qbo-browser"
  },
  {
    "repo_name": "akiroz/re-frame-whatanime"
  },
  {
    "repo_name": "almope/JuegosNavegador.js"
  },
  {
    "repo_name": "altert/openseadragon-zoom"
  },
  {
    "repo_name": "ariefsetya/kopsimpin-home"
  },
  {
    "repo_name": "arnoldthebat/linux-stable"
  },
  {
    "repo_name": "auxesis/unblockus-updater"
  },
  {
    "repo_name": "biomodels/BIOMD0000000421"
  },
  {
    "repo_name": "biomodels/BIOMD0000000466"
  },
  {
    "repo_name": "chraibi/cellular_automata"
  },
  {
    "repo_name": "clawio/service-eosfs-data"
  },
  {
    "repo_name": "darzul/FlexItemDecoration"
  },
  {
    "repo_name": "decaffeinate/coffeescript"
  },
  {
    "repo_name": "desmondhume/objC-learning"
  },
  {
    "repo_name": "dgopstein/deep_enumerable"
  },
  {
    "repo_name": "eskygo/node-sass-binaries"
  },
  {
    "repo_name": "f4bienk/f4bienk.github.io"
  },
  {
    "repo_name": "fntneves/jquery-labelauty"
  },
  {
    "repo_name": "gang-of-bb/movies-angular"
  },
  {
    "repo_name": "gurugithub/kooaba-cadabra"
  },
  {
    "repo_name": "harryoh/harryoh.github.io"
  },
  {
    "repo_name": "haya14busa/underscore.vim"
  },
  {
    "repo_name": "heavenshell/eslint-config"
  },
  {
    "repo_name": "hedgepigdaniel/gnomocracy"
  },
  {
    "repo_name": "ideascube/koombook-doctor"
  },
  {
    "repo_name": "jay3dec/Junior_App_Part_1"
  },
  {
    "repo_name": "jaypratapsingh/Send_Email"
  },
  {
    "repo_name": "jobiols/management-system"
  },
  {
    "repo_name": "josjac/ilumina-gulp-watch"
  },
  {
    "repo_name": "jzoom/jzoom-android-alert"
  },
  {
    "repo_name": "klefevre/kevinlefevre.com"
  },
  {
    "repo_name": "leahbannon/gwuvisualmedia"
  },
  {
    "repo_name": "llr-cta/calin-docker-base"
  },
  {
    "repo_name": "lyang1810/denovo-assembly"
  },
  {
    "repo_name": "markhealey/NodeTwitterAPI"
  },
  {
    "repo_name": "mavcunha/puppet-jetbrains"
  },
  {
    "repo_name": "maximvarentsov/Essentials"
  },
  {
    "repo_name": "mohitsoni/marathon-client"
  },
  {
    "repo_name": "mohsen94/Download-Manager"
  },
  {
    "repo_name": "mrrrgn/filtered_websocket"
  },
  {
    "repo_name": "nguyentuansieu/phutungoto"
  },
  {
    "repo_name": "nishantgupta107/bootstrap"
  },
  {
    "repo_name": "panicinc/PunchClockServer"
  },
  {
    "repo_name": "php-lug/api-documentation"
  },
  {
    "repo_name": "pjmorse/isperformantaword"
  },
  {
    "repo_name": "sirajudheen53/ImageSlider"
  },
  {
    "repo_name": "stackia/unsplash-trending"
  },
  {
    "repo_name": "superjamie/RetroPie-Setup"
  },
  {
    "repo_name": "thisMagpie/atspi-examples"
  },
  {
    "repo_name": "tpalanga/prioritized-todo"
  },
  {
    "repo_name": "vjcagay/vjcagay.github.io"
  },
  {
    "repo_name": "wangwei1237/promises-book"
  },
  {
    "repo_name": "wwwins/RaspberryPi-beacon"
  },
  {
    "repo_name": "AlexArendsen/computercraft"
  },
  {
    "repo_name": "AlexMazaltov/Heroku-Drupal"
  },
  {
    "repo_name": "BCS-io-provision/bcs_nginx"
  },
  {
    "repo_name": "CPTBarbaciccia/chef-knockd"
  },
  {
    "repo_name": "Collabforge/site-shapermit"
  },
  {
    "repo_name": "GerHobbelt/gulp-fncallback"
  },
  {
    "repo_name": "LouizEchi/ace-consultation"
  },
  {
    "repo_name": "Professi/cuteentitymanager"
  },
  {
    "repo_name": "ShinoSaibaru/shell-toolbox"
  },
  {
    "repo_name": "Tataraovoleti/JsonAdvanced"
  },
  {
    "repo_name": "akdasari/eclipse-workspace"
  },
  {
    "repo_name": "ardaozkal/steam_time_idler"
  },
  {
    "repo_name": "avadordi/mass-spectrometry"
  },
  {
    "repo_name": "bagage/cadastre-conflation"
  },
  {
    "repo_name": "boggen/commerce_for_moodle"
  },
  {
    "repo_name": "chrisbaily/congressconnect"
  },
  {
    "repo_name": "chuckwired/ios-scroll-test"
  },
  {
    "repo_name": "cjjavellana/pyJasperClient"
  },
  {
    "repo_name": "divyang4481/nLocalGeocoder"
  },
  {
    "repo_name": "dschwertfeger/book-library"
  },
  {
    "repo_name": "eka-putra/asboot.github.io"
  },
  {
    "repo_name": "emilh91/groupme-api-client"
  },
  {
    "repo_name": "exbb2/text-locale-encoding"
  },
  {
    "repo_name": "featureguardian/fg-service"
  },
  {
    "repo_name": "fungxu/esp-dimmer-software"
  },
  {
    "repo_name": "gaetanHautecoeur/simplyelo"
  },
  {
    "repo_name": "guhanjie/java-common-utils"
  },
  {
    "repo_name": "hacklanta/hubot-yardmaster"
  },
  {
    "repo_name": "htekgulds/zk-spring-sample"
  },
  {
    "repo_name": "ingantoniovillella/Symfony"
  },
  {
    "repo_name": "jesusangel/JAVA-HelloWorld"
  },
  {
    "repo_name": "jreiberkyle/sicp-solutions"
  },
  {
    "repo_name": "jtarchie/sinatra-openresty"
  },
  {
    "repo_name": "jumilla/laravel-addomnipot"
  },
  {
    "repo_name": "karthi-anubavam/cloud-test"
  },
  {
    "repo_name": "konstantinzolotarev/trails"
  },
  {
    "repo_name": "linux-devil/udacity_hadoop"
  },
  {
    "repo_name": "lucasrangit/twitter-winner"
  },
  {
    "repo_name": "markfinger/webpack-watcher"
  },
  {
    "repo_name": "mohsinalimat/SVProgressHUD"
  },
  {
    "repo_name": "monsterlabs/scope_by_fuzzy"
  },
  {
    "repo_name": "notonthehighstreet/feature"
  },
  {
    "repo_name": "oldfartdeveloper/elixir-kv"
  },
  {
    "repo_name": "passick/TCO-hackathon-2015"
  },
  {
    "repo_name": "pquant/haskell-time-series"
  },
  {
    "repo_name": "pulkitjalan/docker-sculpin"
  },
  {
    "repo_name": "rat-leap/ducking-octo-meme"
  },
  {
    "repo_name": "rsekhar19/SecureBoardShare"
  },
  {
    "repo_name": "sakalauskas/backup-manager"
  },
  {
    "repo_name": "shina/control-my-budget-se"
  },
  {
    "repo_name": "stanfordpython/python-labs"
  },
  {
    "repo_name": "sundae24/webgl_experiments"
  },
  {
    "repo_name": "techdude1996/Lego-Importer"
  },
  {
    "repo_name": "trantuanckc/ogilvyone-blog"
  },
  {
    "repo_name": "tulios/css-color-highlight"
  },
  {
    "repo_name": "wedesoft/hornetseye-linalg"
  },
  {
    "repo_name": "zcanter/aframe-scatterplot"
  },
  {
    "repo_name": "0359xiaodong/SimpleCropView"
  },
  {
    "repo_name": "ASOdesk/selenium-pytest-fix"
  },
  {
    "repo_name": "BerndPeuser/Korg-EMX-Editor"
  },
  {
    "repo_name": "CarlosLannister/OwadeReborn"
  },
  {
    "repo_name": "ChrisMacNaughton/rusty_json"
  },
  {
    "repo_name": "DanielHabib/HowManyBalloons"
  },
  {
    "repo_name": "Devilquake/projectWebMobile"
  },
  {
    "repo_name": "HongliYu/PSTAlertController"
  },
  {
    "repo_name": "IgorSantos17/BigBangProject"
  },
  {
    "repo_name": "Jiansen/GDSCalculatorPublic"
  },
  {
    "repo_name": "MarkyC/1stchoicerestoration"
  },
  {
    "repo_name": "Paintface07/angular-example"
  },
  {
    "repo_name": "Pompeu/write-code-every-day"
  },
  {
    "repo_name": "SimonWaldherr/GoRealtimeWeb"
  },
  {
    "repo_name": "TheUltimateMuffin/MineWacke"
  },
  {
    "repo_name": "ZenDevelopmentSystems/pedal"
  },
  {
    "repo_name": "ZenMoore/ZenMoore.github.io"
  },
  {
    "repo_name": "andreamazz/UIView-draggable"
  },
  {
    "repo_name": "boggle/neo4j-haskell-driver"
  },
  {
    "repo_name": "ccalboni/milan-for-tourists"
  },
  {
    "repo_name": "codefellows/Swift-Intensive"
  },
  {
    "repo_name": "d00616/Teensy3SerialMonitor"
  },
  {
    "repo_name": "eiskaltdcpp/eiskaltdcpp-web"
  },
  {
    "repo_name": "emer0306/PortalMiguelServet"
  },
  {
    "repo_name": "fboyer/adventofcode-haskell"
  },
  {
    "repo_name": "flassont/flassont.github.io"
  },
  {
    "repo_name": "goktugyil/EZSwiftExtensions"
  },
  {
    "repo_name": "guowilling/SRPictureBrowser"
  },
  {
    "repo_name": "hoathenguyen85/room_service"
  },
  {
    "repo_name": "ichikawatatsuya/pms_openpne"
  },
  {
    "repo_name": "idiotwithalaptop/dashinator"
  },
  {
    "repo_name": "iskinmike/mwss_robot_module"
  },
  {
    "repo_name": "josephyajo/frame-sample-app"
  },
  {
    "repo_name": "jwbraucher/docker-wordpress"
  },
  {
    "repo_name": "ketilovre/akka-http-macwire"
  },
  {
    "repo_name": "kmihelich/linux-espressobin"
  },
  {
    "repo_name": "kshaffer/MTO-openpeerreview"
  },
  {
    "repo_name": "lglasgow/rrcellars-pug-sass"
  },
  {
    "repo_name": "mesuvash/mesuvash.github.io"
  },
  {
    "repo_name": "neiljmcl/angular-directives"
  },
  {
    "repo_name": "petebachant/wavemaker-calcs"
  },
  {
    "repo_name": "peter-mount/departureboards"
  },
  {
    "repo_name": "phlickey/phlickey.github.io"
  },
  {
    "repo_name": "renlinx007/TypeFaceTextView"
  },
  {
    "repo_name": "runtimerevolution/rankeable"
  },
  {
    "repo_name": "serius-cms/SeriusMenuBundle"
  },
  {
    "repo_name": "spacedog-io/spacedog-js-sdk"
  },
  {
    "repo_name": "svn2github/libtorrent-1_0_x"
  },
  {
    "repo_name": "swisspol/swisspol.github.io"
  },
  {
    "repo_name": "tiwoc/djinni-cache-bug-demo"
  },
  {
    "repo_name": "zacharyr/gps-auto-dashboard"
  },
  {
    "repo_name": "Algomorph/pyboostcvconverter"
  },
  {
    "repo_name": "ArielInfante/HappyHour-Flask"
  },
  {
    "repo_name": "CookiesUnion/cookiesunion.js"
  },
  {
    "repo_name": "FIXTradingCommunity/fixretro"
  },
  {
    "repo_name": "ForbesLindesay/unescape-html"
  },
  {
    "repo_name": "RodriguezMarioUTN/ingSWL2017"
  },
  {
    "repo_name": "WELCOMEMOZILIA/NguyenDucHiep"
  },
  {
    "repo_name": "Xenopathic/spatial-evolution"
  },
  {
    "repo_name": "aepton/python-data-wrangling"
  },
  {
    "repo_name": "axelor/axelor-business-suite"
  },
  {
    "repo_name": "brabbins/januszkorczak-theme"
  },
  {
    "repo_name": "clairehu7/HKPuzzleExperiment"
  },
  {
    "repo_name": "cloudfoundry-incubator/tenus"
  },
  {
    "repo_name": "danielpanteleit/docker-tools"
  },
  {
    "repo_name": "dreamsyntax/FrogGier-Classic"
  },
  {
    "repo_name": "ekalinin/github-markdown-toc"
  },
  {
    "repo_name": "eragonfan125/cuddly-carnival"
  },
  {
    "repo_name": "extertioner/django-mailchimp"
  },
  {
    "repo_name": "feylikurds/EmployeesRegister"
  },
  {
    "repo_name": "flaxtonio/fntp-file-transfer"
  },
  {
    "repo_name": "frague59/django-auth-ldap-ad"
  },
  {
    "repo_name": "frodsan/minitest-activemodel"
  },
  {
    "repo_name": "georapbox/eventdispatcher.js"
  },
  {
    "repo_name": "hownowbrowncow/ripstech-test"
  },
  {
    "repo_name": "iojohnso/node-octopus-deploy"
  },
  {
    "repo_name": "johnnyshields/mongoid_monkey"
  },
  {
    "repo_name": "koutalou/BeaconRegionManager"
  },
  {
    "repo_name": "mpon-workspace/SwiftBondDemo"
  },
  {
    "repo_name": "nickarino/pebble_reminder_js"
  },
  {
    "repo_name": "opencodeacademy/oca-platform"
  },
  {
    "repo_name": "opoloo/jquery_upload_preview"
  },
  {
    "repo_name": "rajarahulray/drag_the_circle"
  },
  {
    "repo_name": "ruben2020/small-haskell-proj"
  },
  {
    "repo_name": "sergio-fry/testing-celluloid"
  },
  {
    "repo_name": "shipshapecode/ember-shepherd"
  },
  {
    "repo_name": "simonbs/BSSwipeTableViewCell"
  },
  {
    "repo_name": "simonneedham/is-there-a-list"
  },
  {
    "repo_name": "sitdh/cu-database-management"
  },
  {
    "repo_name": "taiki45/ruboty-japan_weather"
  },
  {
    "repo_name": "thermistor/ansible-rails_app"
  },
  {
    "repo_name": "tomizimobile/AsyncDisplayKit"
  },
  {
    "repo_name": "vaadin/atmosphere-javascript"
  },
  {
    "repo_name": "zakthompson/switch-wordpress"
  },
  {
    "repo_name": "AdaByronLovelace/web-template"
  },
  {
    "repo_name": "DustinArmstrong/fullpage.scss"
  },
  {
    "repo_name": "FinishMyTattoo/FinishMyTattoo"
  },
  {
    "repo_name": "LarryBattle/Cash-Dispenser.js"
  },
  {
    "repo_name": "PistonDevelopers/graphics-lab"
  },
  {
    "repo_name": "RipcordSoftware/HttpWebServer"
  },
  {
    "repo_name": "RoryBecker/CR_AttributeTabber"
  },
  {
    "repo_name": "TFK1410/Linux-Adv-Com-Project"
  },
  {
    "repo_name": "VidasContadas/nomesevoces_viz"
  },
  {
    "repo_name": "Zheng-Yejian/xyplayer-package"
  },
  {
    "repo_name": "ajit-kumar-azad/tableau-extjs"
  },
  {
    "repo_name": "andela-blawrence/DMS-REST-API"
  },
  {
    "repo_name": "arstropica/social-media-icons"
  },
  {
    "repo_name": "brandonhimpfen/GitHub-Buttons"
  },
  {
    "repo_name": "btbuxton/sonic-pi-experiments"
  },
  {
    "repo_name": "code-seed/seed-gulp-es6-babel"
  },
  {
    "repo_name": "crcunningham/JROperationQueue"
  },
  {
    "repo_name": "dabowheel/http-client-promise"
  },
  {
    "repo_name": "databricks/spark-pr-dashboard"
  },
  {
    "repo_name": "dblia/elastic-rolling-restart"
  },
  {
    "repo_name": "denislutz/google-api-calendar"
  },
  {
    "repo_name": "devttys1/Crestron-Temperature"
  },
  {
    "repo_name": "drudge/passport-twitter-token"
  },
  {
    "repo_name": "dsandstrom/atom-ekini-like-ui"
  },
  {
    "repo_name": "eviratec/nautilus-replacement"
  },
  {
    "repo_name": "funnelcity/www.funnelcity.com"
  },
  {
    "repo_name": "grigoriy/mnemonic-numbers-rus"
  },
  {
    "repo_name": "hkelf/DiaporamaOfTheInternets"
  },
  {
    "repo_name": "hori64/OpenTX21_magyar-hangok"
  },
  {
    "repo_name": "jimjeffers/UIImage-Categories"
  },
  {
    "repo_name": "jlegrand62/multivarclustering"
  },
  {
    "repo_name": "kijin/gnuboard-session-shield"
  },
  {
    "repo_name": "mallikarjunayaddala/simplecov"
  },
  {
    "repo_name": "mallikarjunayaddala/simplecov"
  },
  {
    "repo_name": "marinoguzman/DIY-with-TI-2015"
  },
  {
    "repo_name": "mkalam-alami/inventory-tweaks"
  },
  {
    "repo_name": "morikat/node-red-contrib-nats"
  },
  {
    "repo_name": "nuryudipurnomo/Pleasure-theme"
  },
  {
    "repo_name": "othercodes/files-upload-class"
  },
  {
    "repo_name": "pmoelgaard/language_detection"
  },
  {
    "repo_name": "pqpo/android.asyncImageLoader"
  },
  {
    "repo_name": "ros-industrial/industrial_pcl"
  },
  {
    "repo_name": "soloproyectos-php/http-upload"
  },
  {
    "repo_name": "ssuryakumar/social-network-wp"
  },
  {
    "repo_name": "strahlex/QtQuickVcpHelloWorld"
  },
  {
    "repo_name": "swan0/react-pages-boilerplate"
  },
  {
    "repo_name": "tuanhuynh/tuanhuynh.github.io"
  },
  {
    "repo_name": "westke/gallery-by-react-study"
  },
  {
    "repo_name": "CaptainBipto/ConnectingCouples"
  },
  {
    "repo_name": "DeusExMachina/Task-Prioritizer"
  },
  {
    "repo_name": "Frapwings/fendjs-router-client"
  },
  {
    "repo_name": "JuliaPackageMirrors/Pardiso.jl"
  },
  {
    "repo_name": "RevisionUpdates-CS/HTML-Sample"
  },
  {
    "repo_name": "aestasit/sectioned-view-plugin"
  },
  {
    "repo_name": "alanbrady/image-editing-webapp"
  },
  {
    "repo_name": "avernois/prez-before_after_tdd"
  },
  {
    "repo_name": "blackbirdtech/merlin-typeahead"
  },
  {
    "repo_name": "blissbooker/hapi-error-wrapper"
  },
  {
    "repo_name": "bogdanalbei/krunchy-kreme-core"
  },
  {
    "repo_name": "chaturadilan/carbon-dashboards"
  },
  {
    "repo_name": "cleblanc87/chef_cookbook_railo"
  },
  {
    "repo_name": "dfensgmbh/biz.dfch.LS.PushMenu"
  },
  {
    "repo_name": "ezpublishlegacy/OWScriptLogger"
  },
  {
    "repo_name": "gabrielrcouto/palestra-ratchet"
  },
  {
    "repo_name": "glenpassow/computerProgramming"
  },
  {
    "repo_name": "globaltalentgrid/camerapreview"
  },
  {
    "repo_name": "jeffisabelle/EN4S-presentation"
  },
  {
    "repo_name": "lamastex/scalable-data-science"
  },
  {
    "repo_name": "mkjasinski/spring-boot-example"
  },
  {
    "repo_name": "mmarkov/SoftServeInc.github.io"
  },
  {
    "repo_name": "mozilla-services/data-pipeline"
  },
  {
    "repo_name": "mstarkman/ember-rails-template"
  },
  {
    "repo_name": "nandyala112/AngularJS-Race-APP"
  },
  {
    "repo_name": "nesquena/semantic_form_builder"
  },
  {
    "repo_name": "netproteus/grunt-webp-compress"
  },
  {
    "repo_name": "numa-engineering/python-daemon"
  },
  {
    "repo_name": "openstack-infra/ansible-puppet"
  },
  {
    "repo_name": "rscipien/ClipboardFileTramsfer"
  },
  {
    "repo_name": "scollinspt/activityRecognition"
  },
  {
    "repo_name": "thehogfather/image-map-creator"
  },
  {
    "repo_name": "theteknocat/Biscuit-Navigation"
  },
  {
    "repo_name": "waddedMeat/ember-proxy-example"
  },
  {
    "repo_name": "Aurelsicoko/sails-socket-client"
  },
  {
    "repo_name": "Innarticles/projectFindHospital"
  },
  {
    "repo_name": "MatejBalantic/MBTraitCollection"
  },
  {
    "repo_name": "NabaSadiaSiddiqui/url-shortener"
  },
  {
    "repo_name": "Pataar/generator-js-lib-starter"
  },
  {
    "repo_name": "PratikGarg/pratikgarg.github.io"
  },
  {
    "repo_name": "SafetyCulture/Android-ZXing-Lib"
  },
  {
    "repo_name": "TeamDeverse/peace-corps-android"
  },
  {
    "repo_name": "alexmontesg/datasciencecoursera"
  },
  {
    "repo_name": "arnold-almeida/frontend-starter"
  },
  {
    "repo_name": "blah-sphemy/experiments-on-tixe"
  },
  {
    "repo_name": "etianen/django-uuid-upload-path"
  },
  {
    "repo_name": "eventEmitter/restful-api-client"
  },
  {
    "repo_name": "farr/GWDataAnalysisSummerSchool"
  },
  {
    "repo_name": "frontendkz/frontendkz.github.io"
  },
  {
    "repo_name": "fuzhiqiang1989/ClassyLiveLayout"
  },
  {
    "repo_name": "jeevasusej/bootstrapRowSplitter"
  },
  {
    "repo_name": "jpascoe/laravel-html-dom-parser"
  },
  {
    "repo_name": "jtslear/bug-free-octo-palm-tree"
  },
  {
    "repo_name": "landmarkacoustics/SoundPoints-R"
  },
  {
    "repo_name": "mehdilauters/kodi-qrcode-client"
  },
  {
    "repo_name": "microsec/passbyme2fa-client-php"
  },
  {
    "repo_name": "mustached-pi/mustached-pi-music"
  },
  {
    "repo_name": "patridge/demos-xamarin.ios-tour"
  },
  {
    "repo_name": "sonata-project/SonataCoreBundle"
  },
  {
    "repo_name": "sonountaleban/gpprimitiveengine"
  },
  {
    "repo_name": "suisuiyang/suisuiyang.github.io"
  },
  {
    "repo_name": "whiteoctober/mandango-behaviors"
  },
  {
    "repo_name": "wtrindades/wtrindades.github.io"
  },
  {
    "repo_name": "DJCrossman/backgrid-subgrid-cell"
  },
  {
    "repo_name": "MatthewRueben/elan-video-clipper"
  },
  {
    "repo_name": "Simon-Hohberg/caffe-model-editor"
  },
  {
    "repo_name": "VandalSoftware/android-cache-lib"
  },
  {
    "repo_name": "adamrenner/mqtt-sn-tools-contiki"
  },
  {
    "repo_name": "aitorgrande/Grande-Ingenieros-SL"
  },
  {
    "repo_name": "bwint/GoogleContactsAsteriskSync"
  },
  {
    "repo_name": "cjhoward/cellular-ant-simulation"
  },
  {
    "repo_name": "davidtimovski/soccer-streamlined"
  },
  {
    "repo_name": "fkol-k4/fkol-k4.archlinux.extras"
  },
  {
    "repo_name": "garrizaldy/garrizaldy.github.com"
  },
  {
    "repo_name": "gl3n/HttpQueryStringFilterBundle"
  },
  {
    "repo_name": "gregwhitaker/reactive-sqs-client"
  },
  {
    "repo_name": "huso-io/generator-node-fullstack"
  },
  {
    "repo_name": "jeansch/multi-backgrounds-daemon"
  },
  {
    "repo_name": "markushuber/social-snapshot-tool"
  },
  {
    "repo_name": "mindbrix/UIDynamicsViewInspector"
  },
  {
    "repo_name": "ninjin/bionlp_st_2013_supporting"
  },
  {
    "repo_name": "sovello/CollectCleanData_Project"
  },
  {
    "repo_name": "AlexanderGarmash/Economika-5-year"
  },
  {
    "repo_name": "Apoc70/Set-PersistentPSModulePath"
  },
  {
    "repo_name": "CalinLeafshade/state-of-the-union"
  },
  {
    "repo_name": "DavidSalzer/Mindcet-startups-site"
  },
  {
    "repo_name": "InternetFreedomFoundation/rolodex"
  },
  {
    "repo_name": "MeerkatLabs/Angular-Bowling-Entry"
  },
  {
    "repo_name": "StephaneArguin/my-home-sweet-home"
  },
  {
    "repo_name": "Tontiwisk/numerical-methods-tools"
  },
  {
    "repo_name": "YaroslavShapoval/test--first-task"
  },
  {
    "repo_name": "afronski/localhost-with-chef-solo"
  },
  {
    "repo_name": "ampedandwired/bamboo-mutex-plugin"
  },
  {
    "repo_name": "blowekamp/itkLocalDiscreteHessian"
  },
  {
    "repo_name": "elationfoundation/Reporta-Android"
  },
  {
    "repo_name": "gianina18/boykulit04-yahoo.com.ph"
  },
  {
    "repo_name": "hshah8831/simple-calculator-skill"
  },
  {
    "repo_name": "insanj/ContentTableViewController"
  },
  {
    "repo_name": "karma-exchange-org/karma-exchange"
  },
  {
    "repo_name": "liamgh/liamgreenhughes-sl4a-tf101"
  },
  {
    "repo_name": "liaogz82/locust-fabric-deployment"
  },
  {
    "repo_name": "netconstructor/adwords-php-client"
  },
  {
    "repo_name": "nico-arianto/python-docker-travis"
  },
  {
    "repo_name": "nikita-volkov/json-ast-quickcheck"
  },
  {
    "repo_name": "pankajparkar/bug-tracker-material"
  },
  {
    "repo_name": "prefeiturasp/programa-de-metas-wp"
  },
  {
    "repo_name": "ramkrishna757575/SunshineWearable"
  },
  {
    "repo_name": "sslim/android_kernel_asus_grouper"
  },
  {
    "repo_name": "szymonm/pyspark-dataproc-workshop"
  },
  {
    "repo_name": "theelectricbrain/ROMS-Tidal-Array"
  },
  {
    "repo_name": "treejames/Android-Anim-Playground"
  },
  {
    "repo_name": "tschabo/arduino-silabs-falsh-tool"
  },
  {
    "repo_name": "twohlix/database_cached_attribute"
  },
  {
    "repo_name": "ChattanoogaPublicLibrary/ArduinOps"
  },
  {
    "repo_name": "DreamersTraders/generator-dreambot"
  },
  {
    "repo_name": "FAOSTAT/faostat-ui-metadata-editor"
  },
  {
    "repo_name": "Poket-Jony/TS3ClientQueryFramework"
  },
  {
    "repo_name": "TheExorcist/game-of-life-in-python"
  },
  {
    "repo_name": "TheInfamousBonBon/TIBB-Scripts-Ace"
  },
  {
    "repo_name": "app-guru/dotnet-core-angular-4-cli"
  },
  {
    "repo_name": "bennettp123/dns.ne.net-updater-mac"
  },
  {
    "repo_name": "cornelius-agrippa/tmbox-downloader"
  },
  {
    "repo_name": "eshwaric/EshwariShoreDitchAIPlayer"
  },
  {
    "repo_name": "forcewake/articles-for-translation"
  },
  {
    "repo_name": "gdejong/laravel-wp-admin-you-tried"
  },
  {
    "repo_name": "himanshuawasthi/dell-ui-components"
  },
  {
    "repo_name": "javiercejudo/oxr-to-linear-presets"
  },
  {
    "repo_name": "kevin-alpine/chorus-models-upgrade"
  },
  {
    "repo_name": "mattiaslinnap/django-partial-index"
  },
  {
    "repo_name": "simplemerchant/simplemerchant-ruby"
  },
  {
    "repo_name": "thebestsophist/Modular-Style-Guide"
  },
  {
    "repo_name": "timothyle97/The-Arduino-Gatekeeper"
  },
  {
    "repo_name": "Emerson2017/Autenticacao-de-Usuario"
  },
  {
    "repo_name": "MartinSeeler/iterm2-material-colors"
  },
  {
    "repo_name": "OCSInventory-NG/OCSInventory-Docker"
  },
  {
    "repo_name": "UALR-CodeTalks/TemplatePresentation"
  },
  {
    "repo_name": "countersoft/App-ItemCreatedNotifier"
  },
  {
    "repo_name": "dangerdespain/node-redis-timeseries"
  },
  {
    "repo_name": "ernesto9223/aws-apigateway-importer"
  },
  {
    "repo_name": "fcclithuania/fcclithuania.github.io"
  },
  {
    "repo_name": "kivy-garden/garden.navigationdrawer"
  },
  {
    "repo_name": "rnplus/ESP8266-relay-board-firmware"
  },
  {
    "repo_name": "stephenyeargin/hubot-fitbit-leaders"
  },
  {
    "repo_name": "udacity/course-front-end-frameworks"
  },
  {
    "repo_name": "varunjoshi91/varunjoshi91.github.io"
  },
  {
    "repo_name": "AOEpeople/Aoe_BackendDefaultLanguage"
  },
  {
    "repo_name": "FloridaLiquorLicenses/LiquorLicenses"
  },
  {
    "repo_name": "PGHS-CP1A-2015/python_koans_kjhansen"
  },
  {
    "repo_name": "Polyconseil/bootstrap-datetimepicker"
  },
  {
    "repo_name": "SuperMap/iClient-Silverlight-Example"
  },
  {
    "repo_name": "atom992/todolite-reactnative-android"
  },
  {
    "repo_name": "chinaykl/android_device_huawei_g620s"
  },
  {
    "repo_name": "doublerobotics/Basic-Control-SDK-iOS"
  },
  {
    "repo_name": "evast/transmart-xnat-importer-plugin"
  },
  {
    "repo_name": "jmharvey1/DDS_AD9850_AntennaAnalyzer"
  },
  {
    "repo_name": "markquezada/heroku-resque-auto-scale"
  },
  {
    "repo_name": "ryansobol/coding_interview_questions"
  },
  {
    "repo_name": "GinRyan/AndroidMp3LameRecorder-gradle"
  },
  {
    "repo_name": "JIC-CSB/python-intro-ipython-notebook"
  },
  {
    "repo_name": "UltimatumKang/android_external_skia-1"
  },
  {
    "repo_name": "cannonherbert/cannonherbert.github.io"
  },
  {
    "repo_name": "codeforamerica/clinical_trials_python"
  },
  {
    "repo_name": "derek-skinner/monokromatik-blue_theme"
  },
  {
    "repo_name": "diegopedro94/QueComemosPruebaConcepto"
  },
  {
    "repo_name": "eucalyptus/eucalyptus-database-server"
  },
  {
    "repo_name": "geekboxzone/mmallow_external_blktrace"
  },
  {
    "repo_name": "jonthomas2011/jonthomas2011.github.io"
  },
  {
    "repo_name": "qnikst/distributed-process-supervisor"
  },
  {
    "repo_name": "rino0601/semantic-ui-react-redux-form"
  },
  {
    "repo_name": "rossbreytberg/rossbreytberg.github.io"
  },
  {
    "repo_name": "snowplow/scalding-snowplow-indicators"
  },
  {
    "repo_name": "stevenmillsii/stevenmillsii.github.io"
  },
  {
    "repo_name": "M1lan/commandline-learning-environment"
  },
  {
    "repo_name": "earlonrails/atom-snowball-syntax-theme"
  },
  {
    "repo_name": "environmentalinformatics-marburg/jacky"
  },
  {
    "repo_name": "fabiancnieto/job_a-p-p_c-l-i-c-kd-eliv"
  },
  {
    "repo_name": "innowatio/iwwa-lambda-sites-aggregator"
  },
  {
    "repo_name": "JesseLeite/Laravel-Bootstrap-Modal-Form"
  },
  {
    "repo_name": "andre-wojtowicz/poznan-mp-interventions"
  },
  {
    "repo_name": "everit-org-archive/osgi-jdbc-postgresql"
  },
  {
    "repo_name": "gilliganondata/r-shiny-google-analytics"
  },
  {
    "repo_name": "jeffrymorris/couchbase-sdk-n1ql-example"
  },
  {
    "repo_name": "mattiamaestrini/spotify-web-api-android"
  },
  {
    "repo_name": "nambrot/blueprint-formatter-example-app"
  },
  {
    "repo_name": "shakeelmohamed/CodedayDecemberResources"
  },
  {
    "repo_name": "sushiandrobots/sushiandrobots.github.io"
  },
  {
    "repo_name": "vezetvsem/react-classname-prefix-loader"
  },
  {
    "repo_name": "Kompassi/Checkout-Finland-Magento-module"
  },
  {
    "repo_name": "MarkPieszak/angular-application-insights"
  },
  {
    "repo_name": "MihaiLiviuCojocar/rock-paper-scissors_js"
  },
  {
    "repo_name": "NordicSemiconductor/IOS-Pods-DFU-Library"
  },
  {
    "repo_name": "appcoreopc/efficient-java-matrix-library"
  },
  {
    "repo_name": "git-patrickliu/responsive-compass-sprite"
  },
  {
    "repo_name": "jbavari/Dont-Be-a-Grunt-Use-Grunt-Slides"
  },
  {
    "repo_name": "JohnVCS/ModifiedDosocsWithMavenDependency"
  },
  {
    "repo_name": "Paytm-Payments/Paytm_App_Checksum_Kit_JSP"
  },
  {
    "repo_name": "ebola777/Verilog-bdf-to-verilog-converter"
  },
  {
    "repo_name": "jasonsturges/openfl-haxe-performance-test"
  },
  {
    "repo_name": "royratcliffe/HypertextApplicationLanguage"
  },
  {
    "repo_name": "sensu-plugins/sensu-plugins-elasticsearch"
  },
  {
    "repo_name": "tomorrow-lauren/tomorrow-lauren.github.io"
  },
  {
    "repo_name": "TeknoloGenie/loopback-connector-quickbooks"
  },
  {
    "repo_name": "darryncampbell/WakeLock_WifiLock_Exerciser"
  },
  {
    "repo_name": "drewrygh/ionic-ion-horizontal-scroll-cards"
  },
  {
    "repo_name": "HariprasadNeeraja/MVC_CatClicker-Javascript"
  },
  {
    "repo_name": "PyramidTechnologies/PInvoke-Printer-Example"
  },
  {
    "repo_name": "haixuanc/headless-end-to-end-testing-docker"
  },
  {
    "repo_name": "hammerandchisel/react-native-webpack-server"
  },
  {
    "repo_name": "EuphoriaOS/android_kernel_samsung_exynos5410"
  },
  {
    "repo_name": "MadhukarSP/biojs-vis-UniprotProteinAlignment"
  },
  {
    "repo_name": "Telerik-NodeJs-Team-1/Cards-Against-Humanity"
  },
  {
    "repo_name": "angular/angular-devkit-build-optimizer-builds"
  },
  {
    "repo_name": "viktormuller/notifications-quickstart-android"
  },
  {
    "repo_name": "amolsharma99/PredictingJobEntityTypeFromString"
  },
  {
    "repo_name": "eblen/Eclipse-CMake-language-settings-provider"
  },
  {
    "repo_name": "jdvermeire/kaggle-click-through-rate-prediction"
  },
  {
    "repo_name": "robdmoore/TestFixtureDataGenerationPresentation"
  },
  {
    "repo_name": "runekaagaard/django-crispy-forms-fancy-formsets"
  },
  {
    "repo_name": "silverstripe-labs/silverstripe-sharedraftcontent"
  },
  {
    "repo_name": "LHSCyberSecurityClub/lhscybersecurityclub.github.io"
  },
  {
    "repo_name": "Sage-Bionetworks/DREAM_Alzheimers_Challenge_Scoring"
  },
  {
    "repo_name": "cowlingj/an-introduction-to-programming-with-python"
  },
  {
    "repo_name": "publishing-systems/automated_digital_publishing_server"
  },
  {
    "repo_name": "solarteknik1/SERVICE-SOLAHART-PASAR-MINGGU-081802966444"
  },
  {
    "repo_name": "Johny-kann/Computer_Graphics_3D_Transformations-Application"
  },
  {
    "repo_name": "kaustav020189/instant-username-availability-validation-check"
  }
]